Workbook

Sheet QUOTATION
W1: MODULE WATTAGE | X1: NO OF MODULE | Y1: TOTAL WP | Z1: TOTAL KW
W2: 630 | X2: 24 | Y2: =X2*W2 -> 15120 | Z2: =Y2/1000 -> 15.12
U3: SR NO | V3: ITEM HEAD | W3: ITEM TYPE | X3: ITEM NAME | Y3: ITEM MAKE | Z3: DESCRIPTION | AA3: UNIT | AB3: RATE W/O GST | AC3: QTY | AD3: TOTAL | AE3: GST % | AF3: TOTAL GST | AG3: RATE WITH GST | AH3: ITEM HEAD
U4: 1 | V4: SOLAR MODULE | W4: TOPCON BI - FACIAL PV MODULE | X4: =Table2[[#This Row],[ITEM TYPE]] -> TOPCON BI - FACIAL PV MODULE | Y4: ADANI | Z4: =VLOOKUP(W4,Inventry!B2:F206,3,FALSE) -> TOPCon (Tunnel Oxide Passivated Contact) bi-facial PV modules are next-generation high-efficiency solar panels that generate power from both front and rear surfaces. These modules utilize advanced n-type cell technology, offering higher efficiency, better low-light performance, and lower degradation rates compared to traditional PERC modules. With bifacial gain ranging from 5% to 25% depending on site conditions, TOPCon modules deliver superior energy output and long-term reliability—ideal for commercial, industrial, and utility-scale installations. | AA4: =VLOOKUP(W4,Inventry!B2:F206,4,FALSE) -> WP | AB4: =VLOOKUP(W4,Inventry!B2:F206,5,FALSE) -> 18 | AC4: =Y2 -> 15120 | AD4: =Table2[[#This Row],[QTY]]*Table2[[#This Row],[RATE W/O GST]] -> 272160 | AE4: 0.05 | AF4: =Table2[[#This Row],[TOTAL]]*Table2[[#This Row],[GST %]] -> 13608 | AG4: =Table2[[#This Row],[TOTAL GST]]+Table2[[#This Row],[TOTAL]] -> 285768 | AH4: SOLAR MODULE
U5: 2 | V5: INVERTER | W5: ON GRID | X5: INV - 15 KW | Y5: =VLOOKUP(X5,Inventry!B3:F207,2,FALSE) -> SOLARYAAN | Z5: =VLOOKUP(X5,Inventry!B3:F207,3,FALSE) -> HIGH YIELD - Lower startup & wider MPPT voltage EASY AND USER FRIENDLY - Fast and easy commissioning via iSolarCloud App SAFE AND RELIABLE Build-in Type II DC & AC SPD C5 anti-corrosion & IP65 Remote firmware updates | AA5: =VLOOKUP(X5,Inventry!B3:F207,4,FALSE) -> Nos | AB5: =VLOOKUP(X5,Inventry!B3:F207,5,FALSE) -> 61000 | AC5: 1 | AD5: =Table2[[#This Row],[QTY]]*Table2[[#This Row],[RATE W/O GST]] -> 61000 | AE5: 0.05 | AF5: =Table2[[#This Row],[TOTAL]]*Table2[[#This Row],[GST %]] -> 3050 | AG5: =Table2[[#This Row],[TOTAL GST]]+Table2[[#This Row],[TOTAL]] -> 64050 | AH5: INVERTER
U6: 3 | V6: MODULE MOUNTING STRUCTURE | W6: Elevated Structure | X6: STR - HDGI 60 MICRON 60X40 | Y6: =VLOOKUP(X6,Inventry!B4:F208,2,FALSE) -> HINDUSTAR | Z6: =VLOOKUP(X6,Inventry!B4:F208,3,FALSE) -> 60 Micrones Hot Dip Galvanized (GI) pipes with 2MM Thickness are steel pipes coated with a layer of zinc through a hot-dip process, providing superior corrosion resistance and long-term durability. These pipes are commonly used in solar mounting structures due to their strength, weather resistance, and maintenance-free performance. Ideal for outdoor solar installations, GI pipes ensure structural stability and extended service life in diverse environmental conditions. | AA6: =VLOOKUP(X6,Inventry!B4:F208,4,FALSE) -> KG | AB6: =VLOOKUP(X6,Inventry!B4:F208,5,FALSE) -> 68 | AC6: 670 | AD6: =Table2[[#This Row],[QTY]]*Table2[[#This Row],[RATE W/O GST]] -> 45560 | AE6: 0.18 | AF6: =Table2[[#This Row],[TOTAL]]*Table2[[#This Row],[GST %]] -> 8200.8 | AG6: =Table2[[#This Row],[TOTAL GST]]+Table2[[#This Row],[TOTAL]] -> 53760.8 | AH6: MODULE MOUNTING STRUCTURE
U7: 4 | X7: STR - HDGI 60 MICRON 40X40 | Y7: =VLOOKUP(X7,Inventry!B5:F209,2,FALSE) -> HINDUSTAR | Z7: =VLOOKUP(X7,Inventry!B5:F209,3,FALSE) -> 60 Micrones Hot Dip Galvanized (GI) pipes with 2MM Thickness are steel pipes coated with a layer of zinc through a hot-dip process, providing superior corrosion resistance and long-term durability. These pipes are commonly used in solar mounting structures due to their strength, weather resistance, and maintenance-free performance. Ideal for outdoor solar installations, GI pipes ensure structural stability and extended service life in diverse environmental conditions. | AA7: =VLOOKUP(X7,Inventry!B5:F209,4,FALSE) -> KG | AB7: =VLOOKUP(X7,Inventry!B5:F209,5,FALSE) -> 67 | AC7: 670 | AD7: =Table2[[#This Row],[QTY]]*Table2[[#This Row],[RATE W/O GST]] -> 44890 | AE7: 0.18 | AF7: =Table2[[#This Row],[TOTAL]]*Table2[[#This Row],[GST %]] -> 8080.2 | AG7: =Table2[[#This Row],[TOTAL GST]]+Table2[[#This Row],[TOTAL]] -> 52970.2
U8: 5 | X8: STR - MONO RAIL | Y8: =VLOOKUP(X8,Inventry!B6:F210,2,FALSE) -> From reputed Manufacturer | Z8: =VLOOKUP(X8,Inventry!B6:F210,3,FALSE) -> The Solar Mono Rail Structure is a streamlined, single-rail mounting system designed for quick and secure installation of solar PV modules. Made from high-strength aluminum or galvanized steel, it offers lightweight construction, corrosion resistance, and structural stability. Ideal for rooftop and ground-mounted systems, mono rail structures reduce installation time and material usage while ensuring optimal panel alignment and wind resistance. | AA8: =VLOOKUP(X8,Inventry!B6:F210,4,FALSE) -> KW | AB8: =VLOOKUP(X8,Inventry!B6:F210,5,FALSE) -> 900 | AC8: 0 | AD8: =Table2[[#This Row],[QTY]]*Table2[[#This Row],[RATE W/O GST]] -> 0 | AE8: 0.18 | AF8: =Table2[[#This Row],[TOTAL]]*Table2[[#This Row],[GST %]] -> 0 | AG8: =Table2[[#This Row],[TOTAL GST]]+Table2[[#This Row],[TOTAL]] -> 0
U9: 6 | V9: BASE PLATE | X9: MS - BASE PLATE 125X125 3 MM | Y9: =VLOOKUP(X9,Inventry!B7:F211,2,FALSE) -> MS MATERIAL | Z9: =VLOOKUP(X9,Inventry!B7:F211,3,FALSE) -> Supply and installation of MS Base Plate, size 125mm x 125mm x 3mm thickness (MS make), fabricated from mild steel with anti-corrosive coating. Suitable for mounting and anchoring of solar module structures on various surfaces. | AA9: =VLOOKUP(X9,Inventry!B7:F211,4,FALSE) -> NOS | AB9: =VLOOKUP(X9,Inventry!B7:F211,5,FALSE) -> 33 | AC9: 12 | AD9: =Table2[[#This Row],[QTY]]*Table2[[#This Row],[RATE W/O GST]] -> 396 | AE9: 0.18 | AF9: =Table2[[#This Row],[TOTAL]]*Table2[[#This Row],[GST %]] -> 71.28 | AG9: =Table2[[#This Row],[TOTAL GST]]+Table2[[#This Row],[TOTAL]] -> 467.28 | AH9: BASE PLATE
U10: 7 | V10: J BOULT | X10: J BOULT - 60X40 | Y10: =VLOOKUP(X10,Inventry!B8:F212,2,FALSE) -> SS 304 MATERIAL | Z10: =VLOOKUP(X10,Inventry!B8:F212,3,FALSE) -> Supply and installation of J Bolt – size 60mm x 40mm (SS 304 make), manufactured from high-strength galvanized steel. Suitable for anchoring solar mounting structures securely to RCC rooftops or foundations, ensuring structural stability. | AA10: =VLOOKUP(X10,Inventry!B8:F212,4,FALSE) -> NOS | AB10: =VLOOKUP(X10,Inventry!B8:F212,5,FALSE) -> 13.5 | AC10: =X2*4 -> 96 | AD10: =Table2[[#This Row],[QTY]]*Table2[[#This Row],[RATE W/O GST]] -> 1296 | AE10: 0.18 | AF10: =Table2[[#This Row],[TOTAL]]*Table2[[#This Row],[GST %]] -> 233.28 | AG10: =Table2[[#This Row],[TOTAL GST]]+Table2[[#This Row],[TOTAL]] -> 1529.28 | AH10: J BOULT
U11: 8 | V11: ANCORE FASTNER | X11: WEDGE ANCORE BOULT | Y11: =VLOOKUP(X11,Inventry!B9:F213,2,FALSE) -> SS 304 MATERIAL | Z11: =VLOOKUP(X11,Inventry!B9:F213,3,FALSE) -> Supply and installation of Wedge Anchor Bolt (SS 304 make), heavy-duty, galvanized steel fastener suitable for anchoring solar mounting structures to RCC surfaces. Provides high pull-out strength, durability, and long-term structural stability in rooftop solar installations. | AA11: =VLOOKUP(X11,Inventry!B9:F213,4,FALSE) -> NOS | AB11: =VLOOKUP(X11,Inventry!B9:F213,5,FALSE) -> 9.5 | AC11: =AC9*4.5 -> 54 | AD11: =Table2[[#This Row],[QTY]]*Table2[[#This Row],[RATE W/O GST]] -> 513 | AE11: 0.18 | AF11: =Table2[[#This Row],[TOTAL]]*Table2[[#This Row],[GST %]] -> 92.34 | AG11: =Table2[[#This Row],[TOTAL GST]]+Table2[[#This Row],[TOTAL]] -> 605.34 | AH11: ANCORE FASTNER
A12: HI - TECH SOLAR SOLUTION Solutions You Can Trust. | U12: 9 | V12: ACDB | W12: 2 STAGE PROTECTION | X12: ACDB - MCB+SPD | Y12: =VLOOKUP(X12,Inventry!B10:F214,2,FALSE) -> MCB - SCHNEIDER / LK (L&T) SPD - FINDER ENCLOSER - (Note - ABS used till 50-60 kW) | Z12: =VLOOKUP(X12,Inventry!B10:F214,3,FALSE) -> The AC Distribution Box (ACDB) is a vital component for managing and protecting the AC output from the solar inverter. It is equipped with: MCB & MCCB for short-circuit and overload protection SPD (Surge Protection Device) to guard against voltage surges This fully integrated ACDB ensures safe, stable, and efficient operation of solar power systems, suitable for residential, commercial, and industrial applications. | AA12: =VLOOKUP(X12,Inventry!B10:F214,4,FALSE) -> wp | AB12: =VLOOKUP(X12,Inventry!B10:F214,5,FALSE) -> 0.5 | AC12: =AC4 -> 15120 | AD12: =Table2[[#This Row],[QTY]]*Table2[[#This Row],[RATE W/O GST]] -> 7560 | AE12: 0.18 | AF12: =Table2[[#This Row],[TOTAL]]*Table2[[#This Row],[GST %]] -> 1360.8 | AG12: =Table2[[#This Row],[TOTAL GST]]+Table2[[#This Row],[TOTAL]] -> 8920.8 | AH12: ACDB
U13: 10 | V13: DCDB | W13: 2 STAGE PROTECTION | X13: DCDB - DC MCB + SPD | Y13: =VLOOKUP(X13,Inventry!B11:F215,2,FALSE) -> DC MCB - SCHNEIDER / LK (L&T) SPD - FINDER | Z13: =VLOOKUP(X13,Inventry!B11:F215,3,FALSE) -> The DC Distribution Box (DCDB) is designed to protect and control the DC output from solar PV modules. It is equipped with: DC MCB (Miniature Circuit Breaker) for protection against overcurrent and short circuits SPD (Surge Protection Device) to protect against voltage surges and lightning-induced spikes This robust and weatherproof DCDB ensures the safe and reliable operation of the solar power system, enhancing overall system durability. | AA13: =VLOOKUP(X13,Inventry!B11:F215,4,FALSE) -> wp | AB13: =VLOOKUP(X13,Inventry!B11:F215,5,FALSE) -> 0.5 | AC13: =AC4 -> 15120 | AD13: =Table2[[#This Row],[QTY]]*Table2[[#This Row],[RATE W/O GST]] -> 7560 | AE13: 0.18 | AF13: =Table2[[#This Row],[TOTAL]]*Table2[[#This Row],[GST %]] -> 1360.8 | AG13: =Table2[[#This Row],[TOTAL GST]]+Table2[[#This Row],[TOTAL]] -> 8920.8 | AH13: DCDB
U14: 11 | V14: LIGHTNING ARRESTOR | W14: Conventional Lightning Arrestor | X14: Conventional Lightning Arrestor | Y14: =VLOOKUP(X14,Inventry!B12:F216,2,FALSE) -> From reputed Manufacturer | Z14: =VLOOKUP(X14,Inventry!B12:F216,3,FALSE) -> Provides conical protection MOC. Copper with required Spikes for Building and Chimneys Protection | AA14: =VLOOKUP(X14,Inventry!B12:F216,4,FALSE) -> NOS | AB14: =VLOOKUP(X14,Inventry!B12:F216,5,FALSE) -> 3500 | AC14: 1 | AD14: =Table2[[#This Row],[QTY]]*Table2[[#This Row],[RATE W/O GST]] -> 3500 | AE14: 0.18 | AF14: =Table2[[#This Row],[TOTAL]]*Table2[[#This Row],[GST %]] -> 630 | AG14: =Table2[[#This Row],[TOTAL GST]]+Table2[[#This Row],[TOTAL]] -> 4130 | AH14: LIGHTNING ARRESTOR
U15: 12 | V15: EARTHING ROAD | W15: COPPER BONDED SOLID ELECTRODE | X15: ERTH - COPPER BONDED SOLID ELECTRODE | Y15: =VLOOKUP(X15,Inventry!B13:F217,2,FALSE) -> AS PER ISI STANDERD MENUFACTURER | Z15: =VLOOKUP(X15,Inventry!B13:F217,3,FALSE) -> Copper Bonded Earth rods made from high tensile low carbon steel by molecularly bonding 99.9% pure copper with a minimum coating thickness of 250 micron System is Corrosion resistant & rated for high fault currents Moisture booster chemical bags provided for low earth resistance Low maintenance on site | AA15: =VLOOKUP(X15,Inventry!B13:F217,4,FALSE) -> NOS | AB15: =VLOOKUP(X15,Inventry!B13:F217,5,FALSE) -> 500 | AC15: 3 | AD15: =Table2[[#This Row],[QTY]]*Table2[[#This Row],[RATE W/O GST]] -> 1500 | AE15: 0.18 | AF15: =Table2[[#This Row],[TOTAL]]*Table2[[#This Row],[GST %]] -> 270 | AG15: =Table2[[#This Row],[TOTAL GST]]+Table2[[#This Row],[TOTAL]] -> 1770 | AH15: EARTHING ROAD
U16: 13 | V16: DC CABLE | W16: =Table2[[#This Row],[ITEM HEAD]] -> DC CABLE | X16: DC 1C X 6.0 SQMM CU.FLEX CABLE | Y16: =VLOOKUP(X16,Inventry!B14:F218,2,FALSE) -> APAR / POLYCAB / RR KABEL / HAVELLS | Z16: =VLOOKUP(X16,Inventry!B14:F218,3,FALSE) -> Supply and laying of DC 1 Core x 6.0 sqmm copper flexible cable (Apar / Polycab / RR Kabel / Havells make), XLPE insulated, UV and weather resistant, suitable for interconnection of solar PV modules and DC circuits. Ensures high conductivity, low voltage drop, and long-term outdoor durability. | AA16: =VLOOKUP(X16,Inventry!B14:F218,4,FALSE) -> MTR | AB16: =VLOOKUP(X16,Inventry!B14:F218,5,FALSE) -> 80 | AC16: 150 | AD16: =Table2[[#This Row],[QTY]]*Table2[[#This Row],[RATE W/O GST]] -> 12000 | AE16: 0.18 | AF16: =Table2[[#This Row],[TOTAL]]*Table2[[#This Row],[GST %]] -> 2160 | AG16: =Table2[[#This Row],[TOTAL GST]]+Table2[[#This Row],[TOTAL]] -> 14160 | AH16: DC CABLE
U17: 14 | V17: AC CABLE | W17: =Table2[[#This Row],[ITEM HEAD]] -> AC CABLE | X17: AC 4 C X 16 SQMM AL.ARM CABLE | Y17: =VLOOKUP(X17,Inventry!B15:F219,2,FALSE) -> APAR / POLYCAB / RR KABEL / HAVELLS | Z17: =VLOOKUP(X17,Inventry!B15:F219,3,FALSE) -> Supply and laying of AC 4 Core x 16 sqmm Aluminium Armoured Cable (Apar / Polycab / RR Kabel / Havells make), XLPE insulated, PVC sheathed, heavy-duty cable suitable for underground or outdoor AC power transmission in solar power systems. Offers mechanical protection, thermal endurance, and reliable performance under load conditions. | AA17: =VLOOKUP(X17,Inventry!B15:F219,4,FALSE) -> MTR | AB17: =VLOOKUP(X17,Inventry!B15:F219,5,FALSE) -> 126.1 | AC17: 100 | AD17: =Table2[[#This Row],[QTY]]*Table2[[#This Row],[RATE W/O GST]] -> 12610 | AE17: 0.18 | AF17: =Table2[[#This Row],[TOTAL]]*Table2[[#This Row],[GST %]] -> 2269.8 | AG17: =Table2[[#This Row],[TOTAL GST]]+Table2[[#This Row],[TOTAL]] -> 14879.8 | AH17: AC CABLE
U18: 15 | V18: AC CABLE- 2 | W18: =Table2[[#This Row],[ITEM HEAD]] -> AC CABLE- 2 | X18: AC 3.5 C X 185 SQMM AL.ARM CABLE | Y18: =VLOOKUP(X18,Inventry!B16:F220,2,FALSE) -> APAR / POLYCAB / RR KABEL / HAVELLS | Z18: =VLOOKUP(X18,Inventry!B16:F220,3,FALSE) -> Supply and laying of AC 3.5 Core x 185 sqmm Aluminium Armoured Cable (Apar / Polycab / RR Kabel / Havells make), XLPE insulated, PVC sheathed, heavy-duty cable suitable for LT power distribution in large-scale solar installations. Ensures high current-carrying capacity, robust mechanical protection, and reliable performance in outdoor and underground applications under continuous load. | AA18: =VLOOKUP(X18,Inventry!B16:F220,4,FALSE) -> MTR | AB18: =VLOOKUP(X18,Inventry!B16:F220,5,FALSE) -> 802.88 | AC18: 0 | AD18: =Table2[[#This Row],[QTY]]*Table2[[#This Row],[RATE W/O GST]] -> 0 | AE18: 0.18 | AF18: =Table2[[#This Row],[TOTAL]]*Table2[[#This Row],[GST %]] -> 0 | AG18: =Table2[[#This Row],[TOTAL GST]]+Table2[[#This Row],[TOTAL]] -> 0 | AH18: AC CABLE- 2
U19: 16 | V19: EARTHING CABLE / STRIP | W19: =Table2[[#This Row],[ITEM HEAD]] -> EARTHING CABLE / STRIP | X19: ERTH 1 C X 4.0 SQMM CU CABLE | Y19: =VLOOKUP(X19,Inventry!B17:F221,2,FALSE) -> INDOCAB | Z19: =VLOOKUP(X19,Inventry!B17:F221,3,FALSE) -> Supply and laying of Earth 1 Core x 4.0 sqmm Copper Cable, PVC insulated, single-core, suitable for effective grounding of solar PV structures and equipment. Provides excellent conductivity, mechanical strength, and reliable fault current dissipation for enhanced system safety. | AA19: =VLOOKUP(X19,Inventry!B17:F221,4,FALSE) -> MTR | AB19: =VLOOKUP(X19,Inventry!B17:F221,5,FALSE) -> 40.341 | AC19: 200 | AD19: =Table2[[#This Row],[QTY]]*Table2[[#This Row],[RATE W/O GST]] -> 8068.2 | AE19: 0.18 | AF19: =Table2[[#This Row],[TOTAL]]*Table2[[#This Row],[GST %]] -> 1452.276 | AG19: =Table2[[#This Row],[TOTAL GST]]+Table2[[#This Row],[TOTAL]] -> 9520.476 | AH19: EARTHING CABLE / STRIP
A20: Detailed Techno-Commercial Proposal | U20: 17 | V20: LA CABLE / STRIP | W20: =Table2[[#This Row],[ITEM HEAD]] -> LA CABLE / STRIP | X20: ERTH 1 C X 16 SQMM ALM.FLEX CABLE | Y20: =VLOOKUP(X20,Inventry!B18:F222,2,FALSE) -> KANBERY / FLEXGUARD / GEONOM | Z20: =VLOOKUP(X20,Inventry!B18:F222,3,FALSE) -> Supply and laying of Earth 1 Core x 16 sqmm Aluminium Flexible Cable, PVC insulated, suitable for earthing of solar structures and LT panels. Provides cost-effective grounding solution with adequate conductivity and flexibility for reliable fault current dissipation and system safety. | AA20: =VLOOKUP(X20,Inventry!B18:F222,4,FALSE) -> MTR | AB20: =VLOOKUP(X20,Inventry!B18:F222,5,FALSE) -> 20 | AC20: 100 | AD20: =Table2[[#This Row],[QTY]]*Table2[[#This Row],[RATE W/O GST]] -> 2000 | AE20: 0.18 | AF20: =Table2[[#This Row],[TOTAL]]*Table2[[#This Row],[GST %]] -> 360 | AG20: =Table2[[#This Row],[TOTAL GST]]+Table2[[#This Row],[TOTAL]] -> 2360 | AH20: LA CABLE / STRIP
U21: 18 | V21: CABLE TRAY | W21: =Table2[[#This Row],[ITEM HEAD]] -> CABLE TRAY | X21: FRP Cable TraySize: (W) 50mm x(H)50mm x (T)3mm | Y21: =VLOOKUP(X21,Inventry!B19:F223,2,FALSE) -> FRP | Z21: =VLOOKUP(X21,Inventry!B19:F223,3,FALSE) -> Supply and installation of FRP Cable Tray, size 50mm (W) x 50mm (H) x 3mm (T) – FRP make, corrosion-resistant, UV-stabilized, and lightweight. Suitable for safe and durable routing of DC/AC cables in solar power installations under harsh outdoor conditions. | AA21: =VLOOKUP(X21,Inventry!B19:F223,4,FALSE) -> MTR | AB21: =VLOOKUP(X21,Inventry!B19:F223,5,FALSE) -> 230 | AC21: 0 | AD21: =Table2[[#This Row],[QTY]]*Table2[[#This Row],[RATE W/O GST]] -> 0 | AE21: 0.18 | AF21: =Table2[[#This Row],[TOTAL]]*Table2[[#This Row],[GST %]] -> 0 | AG21: =Table2[[#This Row],[TOTAL GST]]+Table2[[#This Row],[TOTAL]] -> 0 | AH21: CABLE TRAY
U22: 19 | V22: CONDUITE | W22: =Table2[[#This Row],[ITEM HEAD]] -> CONDUITE | X22: 35MM PVC CONDUITE | Y22: =VLOOKUP(X22,Inventry!B20:F224,2,FALSE) -> VARDHMAN | Z22: =VLOOKUP(X22,Inventry!B20:F224,3,FALSE) -> Supply and laying of 35mm PVC Conduit, ISI-marked, heavy-duty, UV-resistant and weatherproof, suitable for secure routing and protection of multiple AC/DC cables in solar power installations, both rooftop and ground-mounted. | AA22: =VLOOKUP(X22,Inventry!B20:F224,4,FALSE) -> NOS | AB22: =VLOOKUP(X22,Inventry!B20:F224,5,FALSE) -> 110 | AC22: 50 | AD22: =Table2[[#This Row],[QTY]]*Table2[[#This Row],[RATE W/O GST]] -> 5500 | AE22: 0.18 | AF22: =Table2[[#This Row],[TOTAL]]*Table2[[#This Row],[GST %]] -> 990 | AG22: =Table2[[#This Row],[TOTAL GST]]+Table2[[#This Row],[TOTAL]] -> 6490 | AH22: CONDUITE
A23: =Z2 -> 15.12 | D23: Kwp Roof top Solar System | U23: 20 | V23: WALK WAY | W23: =Table2[[#This Row],[ITEM HEAD]] -> WALK WAY | X23: FRP Solar Walkway - Size: (W) 272mm x (L)3660mm x (H)25mm,Mesh Size: 38mm x 38mm | Y23: =VLOOKUP(X23,Inventry!B21:F225,2,FALSE) -> FRP | Z23: =VLOOKUP(X23,Inventry!B21:F225,3,FALSE) -> Supply and installation of FRP Solar Walkway, size 272mm (W) x 3660mm (L) x 25mm (H), with mesh size 38mm x 38mm. Made from corrosion-resistant, UV-stabilized fiber-reinforced plastic, suitable for safe and durable access pathways between solar module rows on rooftops or ground-mounted structures. | AA23: =VLOOKUP(X23,Inventry!B21:F225,4,FALSE) -> MTR | AB23: =VLOOKUP(X23,Inventry!B21:F225,5,FALSE) -> 370 | AC23: =X2*1.13 -> 27.12 | AD23: =Table2[[#This Row],[QTY]]*Table2[[#This Row],[RATE W/O GST]] -> 10034.4 | AE23: 0.18 | AF23: =Table2[[#This Row],[TOTAL]]*Table2[[#This Row],[GST %]] -> 1806.192 | AG23: =Table2[[#This Row],[TOTAL GST]]+Table2[[#This Row],[TOTAL]] -> 11840.592 | AH23: WALK WAY
U24: 21 | V24: MC4 CONNECTOR | W24: =Table2[[#This Row],[ITEM HEAD]] -> MC4 CONNECTOR | X24: MC4 CONNECTORS | Y24: =VLOOKUP(X24,Inventry!B22:F226,2,FALSE) -> NIGBO | Z24: =VLOOKUP(X24,Inventry!B22:F226,3,FALSE) -> Supply and installation of MC4 connectors, UV-resistant and IP67-rated, suitable for secure and weatherproof DC cable connections in solar PV systems. Ensures reliable plug-and-play connectivity between solar modules and string cables with minimal power loss. | AA24: =VLOOKUP(X24,Inventry!B22:F226,4,FALSE) -> NOS | AB24: =VLOOKUP(X24,Inventry!B22:F226,5,FALSE) -> 32 | AC24: 10 | AD24: =Table2[[#This Row],[QTY]]*Table2[[#This Row],[RATE W/O GST]] -> 320 | AE24: 0.18 | AF24: =Table2[[#This Row],[TOTAL]]*Table2[[#This Row],[GST %]] -> 57.6 | AG24: =Table2[[#This Row],[TOTAL GST]]+Table2[[#This Row],[TOTAL]] -> 377.6 | AH24: MC4 CONNECTOR
U25: 22 | V25: ISOLATION | W25: =Table2[[#This Row],[ITEM HEAD]] -> ISOLATION | X25: ISOLATOR SWITCH | AA25: RS/WATT | AB25: 0.1 | AC25: =AC4 -> 15120 | AD25: =Table2[[#This Row],[QTY]]*Table2[[#This Row],[RATE W/O GST]] -> 1512 | AE25: 0.18 | AF25: =Table2[[#This Row],[TOTAL]]*Table2[[#This Row],[GST %]] -> 272.16 | AG25: =Table2[[#This Row],[TOTAL GST]]+Table2[[#This Row],[TOTAL]] -> 1784.16 | AH25: ISOLATION
B26: Client Name : | E26: LAND MARK | U26: 23 | V26: FOUNDATION BLOCK | Y26: HTSS SCOPE | Z26: RCC Foundation Block – 400x400x400 mm, M25 grade concrete | AA26: NOS | AB26: 300 | AC26: 8 | AD26: =Table2[[#This Row],[QTY]]*Table2[[#This Row],[RATE W/O GST]] -> 2400 | AE26: 0.18 | AF26: =Table2[[#This Row],[TOTAL]]*Table2[[#This Row],[GST %]] -> 432 | AG26: =Table2[[#This Row],[TOTAL GST]]+Table2[[#This Row],[TOTAL]] -> 2832 | AH26: FOUNDATION BLOCK
U27: 24 | V27: OTHER MISS. ITEM | AA27: RS/WATT | AB27: 0.2 | AC27: =AC4 -> 15120 | AD27: =Table2[[#This Row],[QTY]]*Table2[[#This Row],[RATE W/O GST]] -> 3024 | AE27: 0.18 | AF27: =Table2[[#This Row],[TOTAL]]*Table2[[#This Row],[GST %]] -> 544.32 | AG27: =Table2[[#This Row],[TOTAL GST]]+Table2[[#This Row],[TOTAL]] -> 3568.32 | AH27: OTHER MISS. ITEM
B28: Prepared for : | E28: =E26 -> LAND MARK | U28: 25 | V28: Transport | AA28: LS | AB28: 0.3 | AC28: =AC4 -> 15120 | AD28: =Table2[[#This Row],[QTY]]*Table2[[#This Row],[RATE W/O GST]] -> 4536 | AE28: 0.18 | AF28: =Table2[[#This Row],[TOTAL]]*Table2[[#This Row],[GST %]] -> 816.48 | AG28: =Table2[[#This Row],[TOTAL GST]]+Table2[[#This Row],[TOTAL]] -> 5352.48 | AH28: Transport
U29: 26 | V29: Installation Charges | AA29: KW | AB29: 1700 | AC29: =AC4/1000 -> 15.12 | AD29: =Table2[[#This Row],[QTY]]*Table2[[#This Row],[RATE W/O GST]] -> 25704 | AE29: 0.18 | AF29: =Table2[[#This Row],[TOTAL]]*Table2[[#This Row],[GST %]] -> 4626.72 | AG29: =Table2[[#This Row],[TOTAL GST]]+Table2[[#This Row],[TOTAL]] -> 30330.72 | AH29: Installation Charges
B30: Customer Contact Person : | U30: 27 | V30: IFP CHARGES | AA30: RS/KW | AB30: 350 | AC30: =AC29 -> 15.12 | AD30: =Table2[[#This Row],[QTY]]*Table2[[#This Row],[RATE W/O GST]] -> 5292 | AE30: 0.18 | AF30: =Table2[[#This Row],[TOTAL]]*Table2[[#This Row],[GST %]] -> 952.56 | AG30: =Table2[[#This Row],[TOTAL GST]]+Table2[[#This Row],[TOTAL]] -> 6244.56 | AH30: IFP CHARGES
U31: 28 | V31: EARTHING BOARING CHARGES | AA31: NOS | AB31: 0 | AC31: 6 | AD31: =Table2[[#This Row],[QTY]]*Table2[[#This Row],[RATE W/O GST]] -> 0 | AE31: 0.18 | AF31: =Table2[[#This Row],[TOTAL]]*Table2[[#This Row],[GST %]] -> 0 | AG31: =Table2[[#This Row],[TOTAL GST]]+Table2[[#This Row],[TOTAL]] -> 0 | AH31: EARTHING BOARING CHARGES
B32: Type of Consumer: | E32: LT Consumet | U32: 29 | V32: SUB TOTAL | AB32: =SUBTOTAL(109,AB4:AB31) -> 70271.921 | AD32: =SUBTOTAL(109,AD4:AD31) -> 538935.6 | AE32: 0.18 | AF32: =SUBTOTAL(109,AF4:AF31) -> 53697.608 | AG32: =SUBTOTAL(109,AG4:AG31) -> 592633.21 | AH32: SUB TOTAL
U33: 30 | V33: COMMISSIONING AND TESTING | AG33: 0.15 | AH33: COMMISSIONING AND TESTING
B34: Consumer Number : | U34: 31 | AG34: =AG32*AG33 -> 88894.981
U35: 32 | V35: FINAL VALUE | AG35: =AG32+Table2[[#Totals],[RATE WITH GST]] -> 681528.19 | AH35: FINAL VALUE
B36: Prepared by : | E36: Er. Ilyas Kaydawala
B38: HTSS Contact Person Name & Contact Numbers | E38: Mr. Ilyas Kaydawala | H38: 8140535380 | I38: 8140535380
E39: Mr. Ammar Kotawala | H39: 8128491230 | I39: 8128491230
E40: Mr. Husain Kotawala | H40: 7069822153 | I40: 7069822153
E41: Mob: +91-8140535380, Email : hitechsolarsolu@gmail.com
B42: Date of Issue : | E42: =TODAY() -> 46043
B44: Valid Till Date : | E44: 10 Days from date of issue.
A49: Executive Summary:
A50: We are pleased to present our proposal for the installation of a solar power plant at your facility. This project is designed to help your organization reduce electricity costs, lower carbon emissions, and move towards long-term energy sustainability. Our comprehensive solution covers all aspects of the project—from design and procurement to installation, commissioning, and post-installation support. By partnering with us, you gain access to industry-leading technology, quality workmanship, and professional project management. The solar power system will be installed as per applicable regulations and safety standards, and is structured to operate efficiently over its entire lifecycle. Our team ensures seamless coordination with local authorities and utility providers to facilitate net metering and necessary approvals. This proposal outlines the commercial terms, implementation plan, warranty coverage, and after-sales support details. It reflects our commitment to delivering reliable, cost-effective, and environmentally responsible energy solutions tailored to your business needs. We look forward to working with you and contributing to your sustainability goals.
A67: Description of Services:
A68: We propose to provide the following services for the installation of a solar plant:
A69: Engineering Detailed site survey and feasibility analysis. & Design of the solar power plant, including electrical and structural engineering. Procurement Procurement of all necessary components and materials, including: Solar PV modules, Inverters (string or central), Mounting structures, Cables, connectors, and junction boxes, switchgear, and protection systems All components shall comply with applicable quality standards (e.g., BIS, IEC). Construction & Installation Civil and structural works, including foundations and mounting systems, Mechanical installation of modules and mounting structures, Electrical installation, including cabling, inverter integration, earthing, and lightning protection & Synchronization with the grid as per DISCOM/CEIG guidelines. Testing & Commissioning Pre-commissioning checks and testing of all systems, System energization and performance testing, Grid synchronization and approvals from relevant authorities & Preparation and submission of commissioning reports. Testing and Commissioning: We will conduct rigorous testing procedures to ensure the proper functioning of the solar plant before commissioning it for regular operation. Training and Support: We will provide training sessions for your staff on the operation and maintenance of the solar plant. &Additionally, we offer ongoing technical support and maintenance services. Documentation & Approvals Assistance in obtaining necessary statutory approvals (e.g., CEIG, DISCOM, net metering). Preparation of As-Built drawings and final project reports & Warranty certificates, performance guarantees, and handover documents.
A97: Technical Proposal :
A99: Sr No | B99: Parameter | E99: Description | H99: Remarks
A100: 1 | B100: System Size | E100: =CONCATENATE(A23,DATA!N4) -> 15.12Kwp
A101: 2 | B101: System Type | E101: On Grid
A102: 3 | B102: Required Area | E102: =CONCATENATE(QUOTATION!A23*50,DATA!N6) -> 756 Sqft Minimum
A103: 4 | B103: Module Type | E103: =CONCATENATE(W2,DATA!N14,QUOTATION!W4) -> 630WpTOPCON BI - FACIAL PV MODULE | H103: 600WP
B104: Module Make & Rating | E104: =Y4 -> ADANI | H104: Data sheet Attached
B105: Module Efficiency | E105: 0.2138
B106: Product Warranty | E106: 30 years | H106: Linear Power Warranty for 30 years with 2% for 1st year degradation and 0.5% from year 2 to year 30
A107: 5 | B107: Inverter Type | E107: =W5 -> ON GRID | H107: Maximum AC power of 15 kW, a nominal AC power of 10 kW, and a maximum efficiency of 97 %
B108: Inverter Make & Rating | E108: =X5 -> INV - 15 KW | H108: Data sheet Attached
B109: Inverter Warranty Coverage | E109: 5 years from Manufacturer
A110: 6 | B110: Type Of Module Mounting Structure | E110: =W6 -> Elevated Structure | H110: Wind Speed Resistance as per IS 875: up to 120 kmph
B111: Structure Hight (If Elevated Structure) | E111: 10 ft At South , 8 Ft At North
A112: 7 | B112: Array Layout | E112: South Facing, 14° Tilt , Portrait orientation
A113: 8 | B113: Type of ACDB Box | E113: =W12 -> 2 STAGE PROTECTION
A114: 9 | B114: Type of DCDB Box | E114: =W13 -> 2 STAGE PROTECTION
A115: 10 | B115: Type of Lightning Arrestor | E115: =W14 -> Conventional Lightning Arrestor
A116: 11 | B116: Type of Earthing Road | E116: =W15 -> COPPER BONDED SOLID ELECTRODE
A117: 12 | B117: Monitoring System | E117: Remote Monitoring System (Wi-Fi/GPRS), Web & Mobile Interface
A118: 13 | B118: Net Metering Provision | E118: System compatible and provision for Net Metering as per DISCOM norms
A119: 14 | B119: Expected Generation(Unit/Day) | E119: =A23*4 -> 60.48 | H119: 4 | I119: Units/Day/Kw (Generation Guarantee Up to 90%)
A120: 15 | B120: Approvals & Compliance | E120: MNRE, DISCOM, CEIG, IEC/BIS Standards
A121: 16 | B121: Project Completion Timeline | E121: 8 - 10 Weeks from Advance and Site Readiness
A122: A Billing of Quantities
A124: Sr No | B124: Item Name | D124: Make | F124: Description | I124: Unit | J124: Quantity
A125: 1 | B125: SOLAR MODULE | D125: PAHAL | F125: =Z4 -> TOPCon (Tunnel Oxide Passivated Contact) bi-facial PV modules are next-generation high-efficiency solar panels that generate power from both front and rear surfaces. These modules utilize advanced n-type cell technology, offering higher efficiency, better low-light performance, and lower degradation rates compared to traditional PERC modules. With bifacial gain ranging from 5% to 25% depending on site conditions, TOPCon modules deliver superior energy output and long-term reliability—ideal for commercial, industrial, and utility-scale installations. | I125: Nos | J125: =X2 -> 24
A139: 2 | B139: INVERTER | D139: =Y5 -> SOLARYAAN | F139: =Z5 -> HIGH YIELD - Lower startup & wider MPPT voltage EASY AND USER FRIENDLY - Fast and easy commissioning via iSolarCloud App SAFE AND RELIABLE Build-in Type II DC & AC SPD C5 anti-corrosion & IP65 Remote firmware updates | I139: =AA5 -> Nos | J139: 1
A152: 3 | B152: MODULE MOUNTING STRUCTURE | D152: HINDUSTAR | F152: =Z6 -> 60 Micrones Hot Dip Galvanized (GI) pipes with 2MM Thickness are steel pipes coated with a layer of zinc through a hot-dip process, providing superior corrosion resistance and long-term durability. These pipes are commonly used in solar mounting structures due to their strength, weather resistance, and maintenance-free performance. Ideal for outdoor solar installations, GI pipes ensure structural stability and extended service life in diverse environmental conditions. | I152: =AA6 -> KG | J152: =AC6+AC7+AC8 -> 1340
A164: 4 | B164: MAIN AC DISTRIBUTION BOX | D164: =Y12 -> MCB - SCHNEIDER / LK (L&T) SPD - FINDER ENCLOSER - (Note - ABS used till 50-60 kW) | F164: =Z12 -> The AC Distribution Box (ACDB) is a vital component for managing and protecting the AC output from the solar inverter. It is equipped with: MCB & MCCB for short-circuit and overload protection SPD (Surge Protection Device) to guard against voltage surges This fully integrated ACDB ensures safe, stable, and efficient operation of solar power systems, suitable for residential, commercial, and industrial applications. | I164: NOS | J164: 1
A183: 5 | B183: DC DISTRIBUTION BOX | D183: =Y13 -> DC MCB - SCHNEIDER / LK (L&T) SPD - FINDER | F183: =Z13 -> The DC Distribution Box (DCDB) is designed to protect and control the DC output from solar PV modules. It is equipped with: DC MCB (Miniature Circuit Breaker) for protection against overcurrent and short circuits SPD (Surge Protection Device) to protect against voltage surges and lightning-induced spikes This robust and weatherproof DCDB ensures the safe and reliable operation of the solar power system, enhancing overall system durability. | I183: NOS | J183: =J139 -> 1
A195: 6 | B195: ESE LIGHTING ARRESTOR | D195: =X14 -> Conventional Lightning Arrestor | F195: =Z14 -> Provides conical protection MOC. Copper with required Spikes for Building and Chimneys Protection | I195: =AA14 -> NOS | J195: =AC14 -> 1
A214: 7 | B214: =V15 -> EARTHING ROAD | D214: =X15 -> ERTH - COPPER BONDED SOLID ELECTRODE | F214: =Z15 -> Copper Bonded Earth rods made from high tensile low carbon steel by molecularly bonding 99.9% pure copper with a minimum coating thickness of 250 micron System is Corrosion resistant & rated for high fault currents Moisture booster chemical bags provided for low earth resistance Low maintenance on site | I214: =AA15 -> NOS | J214: =AC15 -> 3
A221: 8 | B221: =V16 -> DC CABLE | D221: =Y16 -> APAR / POLYCAB / RR KABEL / HAVELLS | F221: =Z16 -> Supply and laying of DC 1 Core x 6.0 sqmm copper flexible cable (Apar / Polycab / RR Kabel / Havells make), XLPE insulated, UV and weather resistant, suitable for interconnection of solar PV modules and DC circuits. Ensures high conductivity, low voltage drop, and long-term outdoor durability. | I221: Meter | J221: =AC16 -> 150
A228: 9 | B228: =V17 -> AC CABLE | D228: =Y17 -> APAR / POLYCAB / RR KABEL / HAVELLS | F228: =Z17 -> Supply and laying of AC 4 Core x 16 sqmm Aluminium Armoured Cable (Apar / Polycab / RR Kabel / Havells make), XLPE insulated, PVC sheathed, heavy-duty cable suitable for underground or outdoor AC power transmission in solar power systems. Offers mechanical protection, thermal endurance, and reliable performance under load conditions. | I228: Meter | J228: =AC17 -> 100
A237: 10 | B237: =V18 -> AC CABLE- 2 | D237: =Y18 -> APAR / POLYCAB / RR KABEL / HAVELLS | F237: =Z18 -> Supply and laying of AC 3.5 Core x 185 sqmm Aluminium Armoured Cable (Apar / Polycab / RR Kabel / Havells make), XLPE insulated, PVC sheathed, heavy-duty cable suitable for LT power distribution in large-scale solar installations. Ensures high current-carrying capacity, robust mechanical protection, and reliable performance in outdoor and underground applications under continuous load. | I237: Meter | J237: =AC18 -> 0
A247: 11 | B247: =V19 -> EARTHING CABLE / STRIP | D247: =Y19 -> INDOCAB | F247: =Z19 -> Supply and laying of Earth 1 Core x 4.0 sqmm Copper Cable, PVC insulated, single-core, suitable for effective grounding of solar PV structures and equipment. Provides excellent conductivity, mechanical strength, and reliable fault current dissipation for enhanced system safety. | I247: KG/METER | J247: =AC19 -> 200
A254: 12 | B254: =V20 -> LA CABLE / STRIP | D254: =Y20 -> KANBERY / FLEXGUARD / GEONOM | F254: =Z20 -> Supply and laying of Earth 1 Core x 16 sqmm Aluminium Flexible Cable, PVC insulated, suitable for earthing of solar structures and LT panels. Provides cost-effective grounding solution with adequate conductivity and flexibility for reliable fault current dissipation and system safety. | I254: KG/METER | J254: =AC20 -> 100
A261: 13 | B261: =V21 -> CABLE TRAY | D261: =Y21 -> FRP | F261: =Z21 -> Supply and installation of FRP Cable Tray, size 50mm (W) x 50mm (H) x 3mm (T) – FRP make, corrosion-resistant, UV-stabilized, and lightweight. Suitable for safe and durable routing of DC/AC cables in solar power installations under harsh outdoor conditions. | I261: =AA21 -> MTR | J261: =AC21 -> 0
A267: 14 | B267: =V23 -> WALK WAY | D267: =Y23 -> FRP | F267: =Z23 -> Supply and installation of FRP Solar Walkway, size 272mm (W) x 3660mm (L) x 25mm (H), with mesh size 38mm x 38mm. Made from corrosion-resistant, UV-stabilized fiber-reinforced plastic, suitable for safe and durable access pathways between solar module rows on rooftops or ground-mounted structures. | I267: =AA23 -> MTR | J267: =AC23 -> 27.12
A275: 15 | B275: =V26 -> FOUNDATION BLOCK | D275: =Y26 -> HTSS SCOPE | F275: =Z26 -> RCC Foundation Block – 400x400x400 mm, M25 grade concrete | I275: =AA26 -> NOS | J275: =AC26 -> 8
A278: 16 | B278: Fire & Safety | F278: Fire Extinguisher & Sign Bord Marking | I278: Nos | J278: As Per Required
A281: 17 | B281: INSTALLATION & COMMISSIONING | F281: Hi – Tech Solar Solution Scope
A284: Scope of Work Matrix: Rooftop Solar Power Plant
A286: Sr No | B286: Work Item / Activity | E286: Responsibility | G286: Remarks
A288: 1 | B288: Project Development & Engineering
A289: 1.1 | B289: Feasibility Study (technical & financial) | C289: Feasibility Study (technical & financial) | D289: Feasibility Study (technical & financial) | E289: Consumer with EPC Contractor | F289: Consumer with EPC Contractor | G289: Can be jointly discussed with EPC. | H289: Can be jointly discussed with EPC. | I289: Can be jointly discussed with EPC. | J289: Can be jointly discussed with EPC.
A290: 1.2 | B290: Site Survey & Assessment | C290: Site Survey & Assessment | D290: Site Survey & Assessment | E290: EPC Contractor | F290: EPC Contractor | G290: Includes structural and electrical feasibility. | H290: Includes structural and electrical feasibility. | I290: Includes structural and electrical feasibility. | J290: Includes structural and electrical feasibility.
A291: 1.3 | B291: System Design & Engineering Drawings | C291: System Design & Engineering Drawings | D291: System Design & Engineering Drawings | E291: EPC Contractor | F291: EPC Contractor | G291: Electrical SLD, layout, shadow analysis, etc. | H291: Electrical SLD, layout, shadow analysis, etc. | I291: Electrical SLD, layout, shadow analysis, etc. | J291: Electrical SLD, layout, shadow analysis, etc.
A292: 1.4 | B292: Statutory and Safety Compliance (design level) | C292: Statutory and Safety Compliance (design level) | D292: Statutory and Safety Compliance (design level) | E292: EPC Contractor | F292: EPC Contractor | G292: Must follow MNRE, DISCOM, CEIG norms. | H292: Must follow MNRE, DISCOM, CEIG norms. | I292: Must follow MNRE, DISCOM, CEIG norms. | J292: Must follow MNRE, DISCOM, CEIG norms.
A293: 1.5 | B293: Land Levelling and Grading/Tree Cutting | C293: Land Levelling and Grading/Tree Cutting | D293: Land Levelling and Grading/Tree Cutting | E293: Consumer | F293: Consumer | G293: In Consumer Scope | H293: In Consumer Scope | I293: In Consumer Scope | J293: In Consumer Scope
A294: 1.6 | B294: Cable Trenches | C294: Cable Trenches | D294: Cable Trenches | E294: Consumer | F294: Consumer | G294: Existing Trenches considered | H294: Existing Trenches considered | I294: Existing Trenches considered | J294: Existing Trenches considered
A295: 1.7 | B295: Control Rooms (RCC/PEB) | C295: Control Rooms (RCC/PEB) | D295: Control Rooms (RCC/PEB) | E295: Consumer | F295: Consumer | G295: Existing Covered Space in Control Room considered | H295: Existing Covered Space in Control Room considered | I295: Existing Covered Space in Control Room considered | J295: Existing Covered Space in Control Room considered
...

Sheet Inventry
A1: SR NO | B1: ITEM NAME | C1: MAKE | D1: DESCRIPTION | E1: UNIT | F1: RATE
A2: 1 | B2: BI - FACIAL PV MODULE | C2: Adani / VIKRAM SOLAR | D2: Bi-facial photovoltaic (PV) modules are advanced solar panels that generate power from both the front and rear sides. The front side captures direct sunlight, while the rear side absorbs reflected light from surfaces such as the ground or rooftops. This dual-side generation increases overall energy yield by 5% to 30%, depending on site conditions and albedo. | E2: WP | F2: 17
A3: 2 | B3: TOPCON BI - FACIAL PV MODULE | C3: Adani / VIKRAM SOLAR | D3: TOPCon (Tunnel Oxide Passivated Contact) bi-facial PV modules are next-generation high-efficiency solar panels that generate power from both front and rear surfaces. These modules utilize advanced n-type cell technology, offering higher efficiency, better low-light performance, and lower degradation rates compared to traditional PERC modules. With bifacial gain ranging from 5% to 25% depending on site conditions, TOPCon modules deliver superior energy output and long-term reliability—ideal for commercial, industrial, and utility-scale installations. | E3: WP | F3: 18
A4: 3 | B4: MONO FACIAL MODULES | C4: Adani / VIKRAM SOLAR | D4: High-efficiency Monocrystalline Mono Facial Solar PV Module with advanced PERC/half-cut cell technology, durable aluminium frame, tempered glass protection, superior low-light performance, IEC certified, with 25 years performance warranty. | E4: WP | F4: 17
A5: 4 | B5: 630WP TOPCON BI - FACIAL PV MODULE | C5: PAHAL SOLAR | D5: TOPCon (Tunnel Oxide Passivated Contact) bi-facial PV modules are next-generation high-efficiency solar panels that generate power from both front and rear surfaces. These modules utilize advanced n-type cell technology, offering higher efficiency, better low-light performance, and lower degradation rates compared to traditional PERC modules. With bifacial gain ranging from 5% to 25% depending on site conditions, TOPCon modules deliver superior energy output and long-term reliability—ideal for commercial, industrial, and utility-scale installations. | E5: WP | F5: 15.5
A6: 5
A7: 6 | B7: INV - SG3.0RS | C7: SUNGROW | D7: Compatible with high power PV modules Built-in Type II DC & AC SPD IP65, indoor & outdoor installation Lower startup & wider MPPT voltage range Built-in smart PID Zero function One-click access to iSolarCloud monitoring platform Light and compact(A4 Size)with optimized heat dissipation design Real time data (10 seconds refresh sample) Remote firmware updates | E7: Nos | F7: 15800
A8: 7 | B8: INV - SG3.6RS | C8: SUNGROW | D8: Compatible with high power PV modules Built-in Type II DC & AC SPD IP65, indoor & outdoor installation Lower startup & wider MPPT voltage range Built-in smart PID Zero function One-click access to iSolarCloud monitoring platform Light and compact(A4 Size)with optimized heat dissipation design Real time data (10 seconds refresh sample) Remote firmware updates | E8: Nos | F8: 15800
A9: 8 | B9: INV - SG4.0RS | C9: SUNGROW | D9: Compatible with high power PV modules Built-in Type II DC & AC SPD IP65, indoor & outdoor installation Lower startup & wider MPPT voltage range Built-in smart PID Zero function One-click access to iSolarCloud monitoring platform Light and compact(A4 Size)with optimized heat dissipation design Real time data (10 seconds refresh sample) Remote firmware updates | E9: Nos | F9: 24500
A10: 9 | B10: INV - SG5.0RS | C10: SUNGROW | D10: Compatible with high power PV modules Built-in Type II DC & AC SPD IP65, indoor & outdoor installation Lower startup & wider MPPT voltage range Built-in smart PID Zero function One-click access to iSolarCloud monitoring platform Light and compact(A4 Size)with optimized heat dissipation design Real time data (10 seconds refresh sample) Remote firmware updates | E10: Nos | F10: 29000
A11: 10 | B11: INV - SG6.0RS | C11: SUNGROW | D11: Compatible with high power PV modules Built-in Type II DC & AC SPD IP65, indoor & outdoor installation Lower startup & wider MPPT voltage range Built-in smart PID Zero function One-click access to iSolarCloud monitoring platform Light and compact(A4 Size)with optimized heat dissipation design Real time data (10 seconds refresh sample) Remote firmware updates | E11: Nos | F11: 30000
A12: 11 | B12: INV - SG5.0RT | C12: SUNGROW | D12: HIGH YIELD - Lower startup & wider MPPT voltage EASY AND USER FRIENDLY - Fast and easy commissioning via iSolarCloud App SAFE AND RELIABLE Build-in Type II DC & AC SPD C5 anti-corrosion & IP65 Remote firmware updates | E12: Nos
A13: 12 | B13: INV - SG6.0RT | C13: SUNGROW | D13: HIGH YIELD - Lower startup & wider MPPT voltage EASY AND USER FRIENDLY - Fast and easy commissioning via iSolarCloud App SAFE AND RELIABLE Build-in Type II DC & AC SPD C5 anti-corrosion & IP65 Remote firmware updates | E13: Nos | F13: 47000
A14: 13 | B14: INV - SG8.0RT | C14: SUNGROW | D14: HIGH YIELD - Lower startup & wider MPPT voltage EASY AND USER FRIENDLY - Fast and easy commissioning via iSolarCloud App SAFE AND RELIABLE Build-in Type II DC & AC SPD C5 anti-corrosion & IP65 Remote firmware updates | E14: Nos | F14: 51500
A15: 14 | B15: INV - SG10RT | C15: SUNGROW | D15: HIGH YIELD - Lower startup & wider MPPT voltage EASY AND USER FRIENDLY - Fast and easy commissioning via iSolarCloud App SAFE AND RELIABLE Build-in Type II DC & AC SPD C5 anti-corrosion & IP65 Remote firmware updates | E15: Nos | F15: 53500
A16: 15 | B16: INV - SG12RT | C16: SUNGROW | D16: HIGH YIELD - Lower startup & wider MPPT voltage EASY AND USER FRIENDLY - Fast and easy commissioning via iSolarCloud App SAFE AND RELIABLE Build-in Type II DC & AC SPD C5 anti-corrosion & IP65 Remote firmware updates | E16: Nos | F16: 56500
A17: 16 | B17: INV - SG15RT | C17: SUNGROW | D17: HIGH YIELD - Lower startup & wider MPPT voltage EASY AND USER FRIENDLY - Fast and easy commissioning via iSolarCloud App SAFE AND RELIABLE Build-in Type II DC & AC SPD C5 anti-corrosion & IP65 Remote firmware updates | E17: Nos | F17: 66000
A18: 17 | B18: INV - SG20RT | C18: SUNGROW | D18: HIGH YIELD - Lower startup & wider MPPT voltage EASY AND USER FRIENDLY - Fast and easy commissioning via iSolarCloud App SAFE AND RELIABLE Build-in Type II DC & AC SPD C5 anti-corrosion & IP65 Remote firmware updates | E18: Nos | F18: 74000
A19: 18 | B19: INV - SG33CX | C19: SUNGROW | D19: IP66 protection and C5 Anti-corrosion DC Type I+II SPD, AC Type II SPD Support AFCI 2.0 function Key component diagnosis and protection Smart IV Curve Diagnosis Grid fault record function, easy for remote O&M DC 15A current input, compatiable with over 500W+ PV module Dynamic shading optimization mode Built-in PID recovery function | E19: Nos | F19: 119000
A20: 19 | B20: INV - SG50CX-P2 | C20: SUNGROW | D20: IP66 protection and C5 Anti-corrosion DC Type I+II SPD, AC Type II SPD Support AFCI 2.0 function Key component diagnosis and protection Smart IV Curve Diagnosis Grid fault record function, easy for remote O&M DC 15A current input, compatiable with over 500W+ PV module Dynamic shading optimization mode Built-in PID recovery function | E20: Nos | F20: 148000
A21: 20 | B21: INV - SG75CX-P2 | C21: SUNGROW | D21: IP66 and C5 protection Type II SPD for both DC and AC Compliant with global safety and grid code 9 MPPTs with max. efficiency 98.7% Compatible with bifacial module Built-in PID recovery function Touch free commissioning and remote firmware upgrade Online IV curve scan and diagnosis Fuse free design with smart string current monitoring Compatible with Al and Cu AC cables DC 2 in 1 connection enabled Q at night function | E21: Nos | F21: 224000
A22: 21 | B22: INV - SG100CX-P2 | C22: SUNGROW | D22: IP66 and C5 protection Type II SPD for both DC and AC Compliant with global safety and grid code 9 MPPTs with max. efficiency 98.7% Compatible with bifacial module Built-in PID recovery function Touch free commissioning and remote firmware upgrade Online IV curve scan and diagnosis Fuse free design with smart string current monitoring Compatible with Al and Cu AC cables DC 2 in 1 connection enabled Q at night function | E22: Nos | F22: 268000
A23: 22 | B23: INV - SG125CX-P2 | C23: SUNGROW | D23: IP66 and C5 protection Type II SPD for both DC and AC Compliant with global safety and grid code 9 MPPTs with max. efficiency 98.7% Compatible with bifacial module Built-in PID recovery function Touch free commissioning and remote firmware upgrade Online IV curve scan and diagnosis Fuse free design with smart string current monitoring Compatible with Al and Cu AC cables DC 2 in 1 connection enabled Q at night function | E23: Nos | F23: 285000
A24: 23 | B24: INV - 20KW HYBRID | C24: PURE | D24: Capacity-20 kVA Backup time-Up to 18 hours * Standard Warranty-5 years Advanced thermal management system-Yes OUTPUT AC Voltage Regulation (Battery Mode)-415VAC ± 5% Surge Power-36000VA Efficiency (Peak)->97% Switching Modes-On Grid /Off Grid/Hybrid(Optional) Solar Connection-Off Grid/Hybrid Battery Cell Technology-Lithium Ion Qty. of Batteries-5 Nominal Voltage-48V Battery Capacity-20 kWh | E24: NOS | F24: 467000
... A26: 25 | B26: INV - 15 KW | C26: SOLARYAAN | D26: HIGH YIELD - Lower startup & wider MPPT voltage EASY AND USER FRIENDLY - Fast and easy commissioning via iSolarCloud App SAFE AND RELIABLE Build-in Type II DC & AC SPD C5 anti-corrosion & IP65 Remote firmware updates | E26: Nos | F26: 61000
A27: 26
A28: 27
A29: 28
A30: 29
A31: 30
A32: 31 | B32: STR - HDGI 60 MICRON 60X40 | C32: HINDUSTAR | D32: 60 Micrones Hot Dip Galvanized (GI) pipes with 2MM Thickness are steel pipes coated with a layer of zinc through a hot-dip process, providing superior corrosion resistance and long-term durability. These pipes are commonly used in solar mounting structures due to their strength, weather resistance, and maintenance-free performance. Ideal for outdoor solar installations, GI pipes ensure structural stability and extended service life in diverse environmental conditions. | E32: KG | F32: 68
A33: 32 | B33: STR - HDGI 60 MICRON 40X40 | C33: HINDUSTAR | D33: 60 Micrones Hot Dip Galvanized (GI) pipes with 2MM Thickness are steel pipes coated with a layer of zinc through a hot-dip process, providing superior corrosion resistance and long-term durability. These pipes are commonly used in solar mounting structures due to their strength, weather resistance, and maintenance-free performance. Ideal for outdoor solar installations, GI pipes ensure structural stability and extended service life in diverse environmental conditions. | E33: KG | F33: 67
A34: 33 | B34: STR - HDGI 60 MICRON 80X40 | C34: HINDUSTAR | D34: 60 Micrones Hot Dip Galvanized (GI) pipes with 2MM Thickness are steel pipes coated with a layer of zinc through a hot-dip process, providing superior corrosion resistance and long-term durability. These pipes are commonly used in solar mounting structures due to their strength, weather resistance, and maintenance-free performance. Ideal for outdoor solar installations, GI pipes ensure structural stability and extended service life in diverse environmental conditions. | E34: KG | F34: 69
A35: 34 | B35: STR - MONO RAIL | C35: From reputed Manufacturer | D35: The Solar Mono Rail Structure is a streamlined, single-rail mounting system designed for quick and secure installation of solar PV modules. Made from high-strength aluminum or galvanized steel, it offers lightweight construction, corrosion resistance, and structural stability. Ideal for rooftop and ground-mounted systems, mono rail structures reduce installation time and material usage while ensuring optimal panel alignment and wind resistance. | E35: KW | F35: 900
A36: 35 | B36: STR - ELEVATED AL.MONO RAIL | C36: From reputed Manufacturer | D36: The Elevated Aluminum Mono Rail Structure is a lightweight, corrosion-resistant mounting solution designed for solar installations on rooftops or uneven surfaces. Constructed from high-grade anodized aluminum, it provides enhanced elevation for better airflow, easy maintenance access, and improved energy generation through optimal tilt angles. This structure ensures durability, quick installation, and long-term performance with minimal load on the roof. | E36: KW | F36: 1200
A37: 36
A38: 37
A39: 38
A40: 39
A41: 40
A42: 41 | B42: MS - BASE PLATE 125X125 3 MM | C42: MS MATERIAL | D42: Supply and installation of MS Base Plate, size 125mm x 125mm x 3mm thickness (MS make), fabricated from mild steel with anti-corrosive coating. Suitable for mounting and anchoring of solar module structures on various surfaces. | E42: NOS | F42: 33
A43: 42 | B43: MS - BASE PLATE 150X150 4MM | C43: MS MATERIAL | D43: Supply and installation of MS Base Plate, size 150mm x 150mm x 4mm thickness (MS make), made from high-quality mild steel with anti-corrosive coating. Used for secure mounting of solar module support structures on RCC or other foundations. | E43: NOS | F43: 56
A44: 43
A45: 44
A46: 45
A47: 46 | B47: J BOULT - 40X40 | C47: SS 304 MATERIAL | D47: Supply and installation of J Bolt – size 40mm x 40mm (SS 304 make), manufactured from high-strength galvanized steel. Suitable for anchoring solar mounting structures securely to RCC rooftops or foundations, ensuring structural stability. | E47: NOS | F47: 11.5
A48: 47 | B48: J BOULT - 60X40 | C48: SS 304 MATERIAL | D48: Supply and installation of J Bolt – size 60mm x 40mm (SS 304 make), manufactured from high-strength galvanized steel. Suitable for anchoring solar mounting structures securely to RCC rooftops or foundations, ensuring structural stability. | E48: NOS | F48: 13.5
A49: 48
A50: 49
A51: 50
A52: 51 | B52: WEDGE ANCORE BOULT | C52: SS 304 MATERIAL | D52: Supply and installation of Wedge Anchor Bolt (SS 304 make), heavy-duty, galvanized steel fastener suitable for anchoring solar mounting structures to RCC surfaces. Provides high pull-out strength, durability, and long-term structural stability in rooftop solar installations. | E52: NOS | F52: 9.5
A53: 52 | C53: SS 304 MATERIAL | E53: NOS
A54: 53
A55: 54
A56: 55
A57: 56 | B57: ACDB - MCB+MCCB+CONTACTOR+NVR+SPP+SPD+MMF METER | C57: MCB - SCHNEIDER / LK (L&T) MCCB - SCHNEIDER / LK (L&T) CONTACTOR - SCHNEIDER / LK (L&T) NVR - STANDERD SPP - GIC SPD - FINDER MMF METER - SECURE ENCLOSER - (Note - ABS used till 50-60 kW) | D57: The ACDB is a critical component in the solar power system that safely manages and distributes AC power from the inverter to the load or grid. It is equipped with: MCB (Miniature Circuit Breaker) and MCCB (Molded Case Circuit Breaker) for circuit protection Contactor for automatic switching control NVR (No-Volt Release) and SPP (Single Phase Preventer) for protection against phase failure and voltage loss SPD (Surge Protection Device) for protection against voltage surges MMF Meter (Multifunction Meter) for real-time monitoring of voltage, current, power, and energy This fully integrated ACDB ensures system safety, reliable operation, and accurate energy monitoring in solar installations. | E57: wp | F57: 0.7
A58: 57 | B58: ACDB - MCB+MCCB+CONTACTOR+SPD | C58: MCB - SCHNEIDER / LK (L&T) MCCB - SCHNEIDER / LK (L&T) CONTACTOR - SCHNEIDER / LK (L&T) SPD - FINDER ENCLOSER - (Note - ABS used till 50-60 kW) | D58: The AC Distribution Box (ACDB) is designed to distribute and protect the AC output from the solar inverter. It includes: MCB (Miniature Circuit Breaker) and MCCB (Molded Case Circuit Breaker) for overload and short-circuit protection Contactor for automatic load control SPD (Surge Protection Device) to safeguard against voltage spikes and surges This compact and robust ACDB ensures safe, reliable, and efficient operation of the solar power system, meeting electrical safety standards. | E58: wp | F58: 0.6
A59: 58 | B59: ACDB - MCB+MCCB+CONTACTOR+SPD+NVR | C59: MCB - SCHNEIDER / LK (L&T) MCCB - SCHNEIDER / LK (L&T) CONTACTOR - SCHNEIDER / LK (L&T) NVR - STANDERD SPD - FINDER ENCLOSER - (Note - ABS used till 50-60 kW) | D59: The AC Distribution Box (ACDB) is designed to safely distribute the AC power from the solar inverter to the load or utility grid. It includes: MCB & MCCB for overload and short-circuit protection Contactor for automated load switching SPD (Surge Protection Device) for protection against electrical surges NVR (No-Volt Release) for protection against phase loss and ensuring safe re-energization This ACDB ensures reliable operation, enhanced safety, and compliance with standard electrical protection norms in solar power systems. | E59: wp | F59: 0.7
A60: 59 | B60: ACDB - MCB+MCCB+CONTACTOR+SPD+NVR+SPP | C60: MCB - SCHNEIDER / LK (L&T) MCCB - SCHNEIDER / LK (L&T) CONTACTOR - SCHNEIDER / LK (L&T) NVR - STANDERD SPP - GIC SPD - FINDER ENCLOSER - (Note - ABS used till 50-60 kW) | D60: The AC Distribution Box (ACDB) is a vital component for managing and protecting the AC output from the solar inverter. It is equipped with: MCB & MCCB for short-circuit and overload protection Contactor for automatic power switching SPD (Surge Protection Device) to guard against voltage surges NVR (No-Volt Release) for safe restart after power loss SPP (Single Phase Preventer) to protect against phase failure or reverse phase sequence This fully integrated ACDB ensures safe, stable, and efficient operation of solar power systems, suitable for residential, commercial, and industrial applications. | E60: wp | F60: 0.7
A61: 60 | B61: ACDB - MCB+SPD | C61: MCB - SCHNEIDER / LK (L&T) SPD - FINDER ENCLOSER - (Note - ABS used till 50-60 kW) | D61: The AC Distribution Box (ACDB) is a vital component for managing and protecting the AC output from the solar inverter. It is equipped with: MCB & MCCB for short-circuit and overload protection SPD (Surge Protection Device) to guard against voltage surges This fully integrated ACDB ensures safe, stable, and efficient operation of solar power systems, suitable for residential, commercial, and industrial applications. | E61: wp | F61: 0.5
A62: 61
A63: 62
A64: 63
A65: 64
A66: 65
A67: 66 | B67: DCDB - Fuse +SPD | C67: SPD - FNDER FUSE - | D67: The DC Distribution Box (DCDB) is used to safely manage and protect the DC power generated by solar PV modules. It includes: Fuses for overcurrent protection SPD (Surge Protection Device) to safeguard against voltage surges and lightning strikes This compact and durable DCDB ensures safe and reliable operation of the solar system by protecting the inverter and other downstream equipment. | E67: wp | F67: 0.4
A68: 67 | B68: DCDB - DC MCB + SPD | C68: DC MCB - SCHNEIDER / LK (L&T) SPD - FINDER | D68: The DC Distribution Box (DCDB) is designed to protect and control the DC output from solar PV modules. It is equipped with: DC MCB (Miniature Circuit Breaker) for protection against overcurrent and short circuits SPD (Surge Protection Device) to protect against voltage surges and lightning-induced spikes This robust and weatherproof DCDB ensures the safe and reliable operation of the solar power system, enhancing overall system durability. | E68: wp | F68: 0.5
A69: 68 | B69: DCDB - Fuse + MCB + SPD | C69: FUSE - STANDERD DC MCB - SCHNEIDER / LK (L&T) SPD - FINDER | D69: The DC Distribution Box (DCDB) is used to manage and protect the DC power from solar PV modules before it reaches the inverter. It includes: Fuses for string-level overcurrent protection DC MCB (Miniature Circuit Breaker) for additional circuit isolation and safety SPD (Surge Protection Device) to protect against lightning and surge voltages This well-integrated DCDB ensures enhanced safety, system reliability, and protection of downstream equipment in solar PV installations. | E69: wp | F69: 0.5
A70: 69 | B70: DCDB - only Fuse Box | C70: FUSE - STANDERD | D70: The DC Distribution Box (DCDB) with fuse protection is designed to safeguard the DC output from solar PV modules. It includes: DC Fuses for string-level overcurrent protection, ensuring safe operation and preventing damage to the inverter and cables. This basic DCDB offers reliable and cost-effective protection for small to medium-sized solar installations. | E70: wp | F70: 0.35
A71: 70
A72: 71
A73: 72
A74: 73
A75: 74
A76: 75
A77: 76 | B77: Conventional Lightning Arrestor | C77: From reputed Manufacturer | D77: Provides conical protection MOC. Copper with required Spikes for Building and Chimneys Protection | E77: NOS | F77: 3500
A78: 77 | B78: ESE Lightning Arrestor | C78: TORRENT | D78: Lightning is one of the most naturally destructive phenomena. There is no device capable of preventing the formation of lightning, but it is possible to minimize its effects with a lightning protection system. The lightning rod is an essential piece of the lightning protection system. It must be the point of controlled impact of a discharge, so as to provide the lightning current with a path to ground without damaging the The elements that compose an integral lightning protect on system are the following: Air terminals (Early Streamer Emission (ESE) air terminals or Franklin rods and meshed conductors). Down conductors. Earthing. Surge protection. Other measures that minimize the destructive effects of lightning (equipotential bonding, shielding, etc.). | E78: NOS | F78: 9700
A79: 78 | B79: ESE KALRE ALR 01 | C79: KALRE | D79: RP (Radius protection) 71 meter Lightning is one of the most naturally destructive phenomena. There is no device capable of preventing the formation of lightning, but it is possible to minimize its effects with a lightning protection system. The lightning rod is an essential piece of the lightning protection system. It must be the point of controlled impact of a discharge, so as to provide the lightning current with a path to ground without damaging the The elements that compose an integral lightning protect on system are the following: Air terminals (Early Streamer Emission (ESE) air terminals or Franklin rods and meshed conductors). Down conductors. Earthing. Surge protection. Other measures that minimize the destructive effects of lightning (equipotential bonding, shielding, etc.). | E79: NOS | F79: 22000
A80: 79 | B80: ESE KALRE ALR 04 | C80: KALRE | D80: RP (Radius protection) 107 meter Lightning is one of the most naturally destructive phenomena. There is no device capable of preventing the formation of lightning, but it is possible to minimize its effects with a lightning protection system. The lightning rod is an essential piece of the lightning protection system. It must be the point of controlled impact of a discharge, so as to provide the lightning current with a path to ground without damaging the The elements that compose an integral lightning protect on system are the following: Air terminals (Early Streamer Emission (ESE) air terminals or Franklin rods and meshed conductors). Down conductors. Earthing. Surge protection. Other measures that minimize the destructive effects of lightning (equipotential bonding, shielding, etc.). | E80: NOS | F80: 26500
A81: 80 | B81: ESE KALRE STRONG 60 | C81: KALRE | D81: RP (Radius protection) 107 meter Lightning is one of the most naturally destructive phenomena. There is no device capable of preventing the formation of lightning, but it is possible to minimize its effects with a lightning protection system. The lightning rod is an essential piece of the lightning protection system. It must be the point of controlled impact of a discharge, so as to provide the lightning current with a path to ground without damaging the The elements that compose an integral lightning protect on system are the following: Air terminals (Early Streamer Emission (ESE) air terminals or Franklin rods and meshed conductors). Down conductors. Earthing. Surge protection. Other measures that minimize the destructive effects of lightning (equipotential bonding, shielding, etc.). | E81: NOS | F81: 19500
A82: 81 | B82: LA POLE 5 MTR | C82: GI | F82: 7800
A83: 82 | B83: LA POLE 3 MTR | C83: GI | F83: 5000
A84: 83
A85: 84
A86: 85
A87: 86 | B87: ERTH - 50 MM X 3 MTR G.I EARTHING ELECTRODE (PIPE IN STRIP) - MID | C87: AS PER ISI STANDERD MENUFACTURER | D87: Hot dip galvanized pipe with corrosion protection, designed for fast fault current dissipation. Pipe inner space filled with high conductive material with top to bottom strip. Moisture booster chemical bags provided for low earth resistance Low maintenance on site | E87: NOS | F87: 1900
A88: 87 | B88: ERTH - 50 MM X 3 MTR G.I EARTHING ELECTRODE (PIPE IN STRIP) - LIGHT | C88: AS PER ISI STANDERD MENUFACTURER | D88: Hot dip galvanized pipe with corrosion protection, designed for fast fault current dissipation. Pipe inner space filled with high conductive material with top to bottom strip. Moisture booster chemical bags provided for low earth resistance Low maintenance on site | E88: NOS | F88: 1400
A89: 88 | B89: ERTH - 50 MM X 3 MTR G.I EARTHING ELECTRODE (PIPE IN STRIP) - HEAVY | C89: AS PER ISI STANDERD MENUFACTURER | D89: Hot dip galvanized pipe with corrosion protection, designed for fast fault current dissipation. Pipe inner space filled with high conductive material with top to bottom strip. Moisture booster chemical bags provided for low earth resistance Low maintenance on site | E89: NOS | F89: 3400
A90: 89 | B90: ERTH - 76 MM X 3 MTR G.I EARTHING ELECTRODE (PIPE IN STRIP) - MID | C90: AS PER ISI STANDERD MENUFACTURER | D90: Hot dip galvanized pipe with corrosion protection, designed for fast fault current dissipation. Pipe inner space filled with high conductive material with top to bottom strip. Moisture booster chemical bags provided for low earth resistance Low maintenance on site | E90: NOS | F90: 3200
A91: 90 | B91: ERTH - 76 MM X 3 MTR G.I EARTHING ELECTRODE (PIPE IN STRIP) - LIGHT | C91: AS PER ISI STANDERD MENUFACTURER | D91: Hot dip galvanized pipe with corrosion protection, designed for fast fault current dissipation. Pipe inner space filled with high conductive material with top to bottom strip. Moisture booster chemical bags provided for low earth resistance Low maintenance on site | E91: NOS | F91: 2200
A92: 91 | B92: ERTH - 76 MM X 3 MTR G.I EARTHING ELECTRODE (PIPE IN STRIP) - HEAVY | C92: AS PER ISI STANDERD MENUFACTURER | D92: Hot dip galvanized pipe with corrosion protection, designed for fast fault current dissipation. Pipe inner space filled with high conductive material with top to bottom strip. Moisture booster chemical bags provided for low earth resistance Low maintenance on site | E92: NOS | F92: 5500
A93: 92 | B93: ERTH - 50 MM X 3 MTR COPPER BONDED EARTHING ELECTRODE (PIPE IN STRIP) - MID | C93: AS PER ISI STANDERD MENUFACTURER | D93: 250 MICRON COATING pipe with corrosion protection, designed for fast fault current dissipation. Pipe inner space filled with high conductive material with top to bottom strip. Moisture booster chemical bags provided for low earth resistance Low maintenance on site | E93: NOS | F93: 2500
A94: 93 | B94: ERTH - 50 MM X 3 MTR COPPER BONDED EARTHING ELECTRODE (PIPE IN STRIP) - LIGHT | C94: AS PER ISI STANDERD MENUFACTURER | D94: 250 MICRON COATING pipe with corrosion protection, designed for fast fault current dissipation. Pipe inner space filled with high conductive material with top to bottom strip. Moisture booster chemical bags provided for low earth resistance Low maintenance on site | E94: NOS | F94: 1500
A95: 94 | B95: ERTH - 50 MM X 3 MTR COPPER BONDED EARTHING ELECTRODE (PIPE IN STRIP) - HEAVY | C95: AS PER ISI STANDERD MENUFACTURER | D95: 250 MICRON COATING pipe with corrosion protection, designed for fast fault current dissipation. Pipe inner space filled with high conductive material with top to bottom strip. Moisture booster chemical bags provided for low earth resistance Low maintenance on site | E95: NOS | F95: 5400
A96: 95 | B96: ERTH - 76 MM X 3 MTR COPPER BONDED EARTHING ELECTRODE (PIPE IN STRIP) - MID | C96: AS PER ISI STANDERD MENUFACTURER | D96: 250 MICRON COATING pipe with corrosion protection, designed for fast fault current dissipation. Pipe inner space filled with high conductive material with top to bottom strip. Moisture booster chemical bags provided for low earth resistance Low maintenance on site | E96: NOS | F96: 3600
A97: 96 | B97: ERTH - 76 MM X 3 MTR COPPER BONDED EARTHING ELECTRODE (PIPE IN STRIP) - LIGHT | C97: AS PER ISI STANDERD MENUFACTURER | D97: 250 MICRON COATING pipe with corrosion protection, designed for fast fault current dissipation. Pipe inner space filled with high conductive material with top to bottom strip. Moisture booster chemical bags provided for low earth resistance Low maintenance on site | E97: NOS | F97: 2800
A98: 97 | B98: ERTH - 76 MM X 3 MTR COPPER BONDED EARTHING ELECTRODE (PIPE IN STRIP) - HEAVY | C98: AS PER ISI STANDERD MENUFACTURER | D98: 250 MICRON COATING pipe with corrosion protection, designed for fast fault current dissipation. Pipe inner space filled with high conductive material with top to bottom strip. Moisture booster chemical bags provided for low earth resistance Low maintenance on site | E98: NOS | F98: 6400
... A100: 99 | B100: ERTH - COPPER BONDED SOLID ELECTRODE | C100: AS PER ISI STANDERD MENUFACTURER | D100: Copper Bonded Earth rods made from high tensile low carbon steel by molecularly bonding 99.9% pure copper with a minimum coating thickness of 250 micron System is Corrosion resistant & rated for high fault currents Moisture booster chemical bags provided for low earth resistance Low maintenance on site | E100: NOS | F100: 500
A101: 100 | B101: ERTH - PURE COPPER EARTHING ELECTRODE (PIPE IN STRIP) | C101: AS PER ISI STANDERD MENUFACTURER | D101: PURE COPPER PIPE with corrosion protection, designed for fast fault current dissipation. Pipe inner space filled with high conductive material with top to bottom strip. Moisture booster chemical bags provided for low earth resistance Low maintenance on site | E101: NOS
A102: 101
...

Sheet DATA
B1: Structure Hight | C1: Area | D1: Meter Phase | E1: DISCOM | F1: Cost | G1: Module | H1: Type of Solar Module | I1: Month | J1: Unit/Day | K1: Kwh | L1: INR | M1: Type Of Module Mounting Structure | P1: Module Wattage | Q1: No Of Modules | R1: Capacity | S1: Module Cost | T1: Off Grid Inverter Price | U1: Hybrid Inverter Price | W1: Type of Solar Plant:
B2: 1 - 3 | C2: Urban | D2: LT Consumet | E2: MGVCL | F2: 3500 | G2: Adani-530Wp(Bi-Facial) | H2: Mono Bi - Facial | I2: Jan | J2: 4.1 | K2: =QUOTATION!A23*DATA!J2*31 -> 1921.752 | L2: =K2*8 -> 15374.016 | M2: Elevated Structure | N2: Nos | P2: 535 | Q2: 2 | R2: =Q2*P2/1000 -> 1.07 | S2: =20000*Q2 -> 40000 | T2: 15500 | W2: ON GRID
B3: 4-6 | C3: Urban | D3: HT Consumer | E3: UGVCL | F3: 3500 | G3: Adani-540Wp(Bi-Facial) | H3: Topcon Bi - Facial | I3: Jan | J3: 4.6 | K3: =QUOTATION!A23*DATA!J3*31 -> 2156.112 | L3: =K3*8 -> 17248.896 | M3: Mono Rail | N3: Nos | P3: 535 | Q3: 3 | R3: =Q3*P3/1000 -> 1.605 | S3: =20000*Q3 -> 60000 | T3: 17500 | W3: OFF GRID
B4: 6-8 | C4: Rural | D4: LT Consumet | E4: PGVCL | F4: 5500 | G4: Adani-535Wp(Bi-Facial) | I4: Fab | J4: 4.6 | K4: =QUOTATION!A23*DATA!J4*28 -> 1947.456 | L4: =K4*8 -> 15579.648 | N4: Kwp | P4: 535 | Q4: 4 | R4: =Q4*P4/1000 -> 2.14 | S4: =20000*Q4 -> 80000 | T4: 40000 | W4: HYBRID
B5: 8-10 | E5: DGVCL | G5: Adani-570Wp(Bi-Facial) | I5: March | J5: 5 | K5: =QUOTATION!A23*DATA!J5*31 -> 2343.6 | L5: =K5*8 -> 18748.8 | N5: Kw | P5: 535 | Q5: 5 | R5: =Q5*P5/1000 -> 2.675 | S5: =20000*Q5 -> 100000 | T5: 60000
B6: 10-12 | E6: TORRENT | G6: 570wp Topcon (Bi-Facial) | I6: April | J6: 5 | K6: =QUOTATION!A23*DATA!J6*30 -> 2268 | L6: =K6*8 -> 18144 | N6: Sqft Minimum | P6: 535 | Q6: 6 | R6: =Q6*P6/1000 -> 3.21 | S6: =20000*Q6 -> 120000 | T6: 74500
B7: 12-14 | E7: MP Board | G7: 595 Wp Topcon Bi-Facial | I7: May | J7: 5 | K7: =QUOTATION!A23*DATA!J7*31 -> 2343.6 | L7: =K7*8 -> 18748.8 | N7: Feet | P7: 535 | Q7: 7 | R7: =Q7*P7/1000 -> 3.745 | S7: =20000*Q7 -> 140000 | T7: 74500
B8: 18 - 20 | G8: 540Wp Bi-Facial | I8: Jun | J8: 5 | K8: =QUOTATION!A23*DATA!J8*30 -> 2268 | L8: =K8*8 -> 18144 | N8: Degree | P8: 535 | Q8: 8 | R8: =Q8*P8/1000 -> 4.28 | S8: =20000*Q8 -> 160000
B9: NOT MENTIONED | G9: 545 Wp Bi-Facial | I9: July | J9: 4.1 | K9: =QUOTATION!A23*DATA!J9*31 -> 1921.752 | L9: =K9*8 -> 15374.016 | N9: Kwh
G10: 600wp Topcon (Bi-Facial) | I10: Aug | J10: 4.1 | K10: =QUOTATION!A23*DATA!J10*31 -> 1921.752 | L10: =K10*8 -> 15374.016 | N10: INR
I11: Sep | J11: 3.9 | K11: =QUOTATION!A23*DATA!J11*30 -> 1769.04 | L11: =K11*8 -> 14152.32 | N11: kw AC O/P Inverter
I12: Oct | J12: 4.6 | K12: =QUOTATION!A23*DATA!J12*31 -> 2156.112 | L12: =K12*8 -> 17248.896 | N12: Unit
I13: Nov | J13: 4.6 | K13: =QUOTATION!A23*DATA!J13*30 -> 2086.56 | L13: =K13*8 -> 16692.48 | N13: Rupees
I14: Dec | J14: 4.6 | K14: =QUOTATION!A23*DATA!J14*31 -> 2156.112 | L14: =K14*8 -> 17248.896 | N14: Wp
J15: =SUM(J3:J14)/12 -> 4.5916667 | K15: =ROUNDUP(SUM(K3:K14),0) -> 25339 | L15: =ROUNDUP(SUM(L3:L14),0) -> 202705
B18: ACDB | G18: DCDB | H18: LA | I18: Earthing
A19: ACDB | B19: - MCB+MCCB+CONTACTOR+NVR+SPP+SPD+MMF METER | C19: 6 STAGE PROTECTION + MMF METER | E19: 2 STAGE PROTECTION | F19: DCDB | G19: - Fuse +SPD | H19: Conventional Lightning Arrestor | I19: G.I EARTHING ELECTRODE (PIPE IN STRIP) | J19: ERTH - | K19: =CONCATENATE(J19,I19) -> ERTH - G.I EARTHING ELECTRODE (PIPE IN STRIP)
A20: ACDB | B20: - MCB+MCCB+CONTACTOR+SPD | C20: 4 STAGE PROTECTION | E20: 2 STAGE PROTECTION | F20: DCDB | G20: - DC MCB + SPD | H20: ESE Lightning Arrestor | I20: G.I EARTHING ELECTRODE (PIPE IN PIPE) | J20: ERTH - | K20: =CONCATENATE(J20,I20) -> ERTH - G.I EARTHING ELECTRODE (PIPE IN PIPE)
A21: ACDB | B21: - MCB+MCCB+CONTACTOR+SPD+NVR | C21: 5 STAGE PROTECTION | E21: 3 STAGE PROTECTION | F21: DCDB | G21: - Fuse + MCB + SPD | I21: COPPER BONDED EARTHING ELECTRODE (PIPE IN STRIP) | J21: ERTH - | K21: =CONCATENATE(J21,I21) -> ERTH - COPPER BONDED EARTHING ELECTRODE (PIPE IN STRIP)
A22: ACDB | B22: - MCB+MCCB+CONTACTOR+SPD+NVR+SPP | C22: 6 STAGE PROTECTION ( W/O MMF METER ) | E22: SINGLE STAGE PROTECTION | F22: DCDB | G22: - only Fuse Box | I22: PURE COPPER EARTHING ELECTRODE (PIPE IN STRIP) | J22: ERTH - | K22: =CONCATENATE(J22,I22) -> ERTH - PURE COPPER EARTHING ELECTRODE (PIPE IN STRIP)
A23: ACDB | B23: - MCB+SPD | C23: 2 STAGE PROTECTION | E23: =CONCATENATE(F23,G23) | I23: COPPER BONDED SOLID ELECTRODE | J23: ERTH - | K23: =CONCATENATE(J23,I23) -> ERTH - COPPER BONDED SOLID ELECTRODE

Sheet PRICE LIST
A1: Sr No | B1: ITEM NAME | D1: UNIT | E1: RATE | F1: GST | I1: TOTAL
A2: 1 | B2: Module BI FACIAL | D2: RS/WATT | E2: 16 | F2: 0.12 | I2: =E2+(E2*F2) -> 17.92
A3: 2 | B3: Module TOPCON | D3: RS/WATT | E3: 17 | F3: 0.12 | I3: =E3+(E3*F3) -> 19.04
A4: 3 | B4: Inverter | D4: RS/WATT | E4: 5.1 | F4: 0.12 | I4: =E4+(E4*F4) -> 5.712
A5: 4 | B5: Structure = 60 x 40 | D5: Rs/Kw | E5: 4000 | F5: 0.18 | I5: =E5+(E5*F5) -> 4720
A6: 5 | B6: Structure = 40 x 40 | D6: Rs/Kw | E6: 70 | F6: 0.18 | I6: =E6+(E6*F6) -> 82.6
A7: 6 | B7: Base Plate | D7: RS/NOS | E7: 38 | F7: 0.18 | I7: =E7+(E7*F7) -> 44.84
A8: 7 | B8: Ancore Fastner | D8: RS/NOS | E8: 10 | F8: 0.18 | I8: =E8+(E8*F8) -> 11.8
A9: 8 | B9: J Bolt | D9: RS/NOS | E9: 12 | F9: 0.18 | I9: =E9+(E9*F9) -> 14.16
A10: 9 | B10: ACDB | D10: RS/WATT | E10: 0.7 | F10: 0.18 | I10: =E10+(E10*F10) -> 0.826
A11: 10 | B11: DCDB | D11: RS/WATT | E11: 0.5 | F11: 0.18 | I11: =E11+(E11*F11) -> 0.59
A12: 11 | B12: Lighting Arrestor | D12: RS/NOS | E12: 2000 | F12: 0.18 | I12: =E12+(E12*F12) -> 2360
A13: 12 | B13: Earthing Kit | D13: RS/NOS | E13: 1500 | F13: 0.18 | I13: =E13+(E13*F13) -> 1770
A14: 13 | B14: Plant cabaling | D14: RS/Kw | E14: 1200 | F14: 0.18 | I14: =E14+(E14*F14) -> 1416
A15: 14 | B15: AC Wire | D15: RS/MTR | F15: 0.18 | I15: =E15+(E15*F15) -> 0
A16: 15 | B16: DC Wire | D16: RS/MTR | E16: 40.25 | F16: 0.18 | I16: =E16+(E16*F16) -> 47.495
A17: 16 | B17: Eaething Wire | D17: RS/MTR | E17: 32 | F17: 0.18 | I17: =E17+(E17*F17) -> 37.76
A18: 17 | B18: L.A Wire | D18: RS/NOS | E18: 22 | F18: 0.18 | I18: =E18+(E18*F18) -> 25.96
A19: 18 | B19: PVC Pipe | D19: RS/NOS | E19: 65 | F19: 0.18 | I19: =E19+(E19*F19) -> 76.7
A20: 19 | B20: MC4 Connector | D20: RS/NOS | E20: 65 | F20: 0.18 | I20: =E20+(E20*F20) -> 76.7
A21: 20 | B21: Isolation | D21: RS/NOS | F21: 0.18 | I21: =E21+(E21*F21) -> 0
A22: 21 | B22: walk way | D22: RS/SQR MTR | E22: 425 | F22: 0.18 | I22: =E22+(E22*F22) -> 501.5
A23: 22 | B23: Foundation Work | D23: RS/NOS | E23: 350 | F23: 0.18 | I23: =E23+(E23*F23) -> 413
A24: 23 | B24: IFP Charges | D24: RS/KW | E24: 350 | F24: 0.18 | I24: =E24+(E24*F24) -> 413
A25: 24 | B25: Other Miss.Item | D25: RS/KW | E25: 150 | F25: 0.18 | I25: =E25+(E25*F25) -> 177
A26: 25 | B26: Installation Charges | D26: RS/KW | E26: 1700 | F26: 0.18 | I26: =E26+(E26*F26) -> 2006
A27: 26 | B27: Commissioning Charges | F27: 0.12 | I27: =E27+(E27*F27) -> 0
A31: SR NO | B31: NO OF MODULE | C31: MODULE WATTAGE BI FACIAL | D31: DC CAPACITY BI FACIAL | E31: DISCOVER RATE BI FACIAL | F31: GST | G31: FINAL RATE BI FACIAL | H31: MODULE WATTAGE TOPCON | I31: DC CAPACITY TOPCON | J31: DISCOVER RATE TOPCON | K31: GST | L31: FINAL RATE TOPCON | M31: MODULE BI FACIAL | N31: MODULE TOPCON | O31: INVERTER | P31: STRUCTURE | Q31: BASE PLATE | R31: ANCORE FASTNER | S31: J BOULT | T31: ACDB | U31: DCDB | V31: LA | W31: EARTHING ROAD KIT | X31: AC CABLE | Y31: DC CABLE | Z31: LA CABLE | AA31: PVC PIPE | AB31: MC4 CONNECTOR | AC31: ISOLATOR | AD31: WALK WAY | AE31: FOUNDATION | AF31: IFP CHARGES | AG31: OTHER MISS ITEM | AH31: INSTALLATION CHARGES | AI31: TOAL BI FACIAL | AJ31: TOTAL TOPCON | AK31: COMMISSIONING CHARGES | AL31: TOAL BI FACIAL | AM31: TOTAL TOPCON
A32: 1 | B32: 12 | C32: 545 | D32: =B32*C32/1000 -> 6.54 | E32: =AL32/D32 -> 36578.618 | F32: 0.139 | G32: =(E32+(E32*F32))*D32 -> 272476.32 | H32: 580 | I32: =B32*H32/1000 -> 6.96 | J32: =AM32/I32 -> 36572.667 | K32: 0.139 | L32: =(J32+(J32*K32))*I32 -> 289927.62 | M32: =$E$2*(D32*1000) -> 104640 | N32: =$E$3*(I32*1000) -> 118320 | O32: =$E$4*I32*1000 -> 35496 | P32: =$E$5*I32 -> 27840 | Q32: =$E$7*B32 -> 456 | R32: =$E$8*B32 -> 120 | S32: =$E$9*(B32*4) -> 576 | T32: =$E$10*(I32*1000) -> 4872 | U32: =$E$11*(I32*1000) -> 3480 | V32: =$E$12 -> 2000 | W32: =$E$13 -> 1500 | X32: =$E$14*I32 -> 8352 | AB32: =$E$20*(B32/2) -> 390 | AC32: =I32*100 -> 696 | AD32: =$E$22*(B32*1.13) -> 5763 | AE32: =$E$23*(B32/2) -> 2100 | AF32: =$E$24*I32 -> 2436 | AG32: =$E$25*I32 -> 1044 | AH32: =$E$26*I32 -> 11832 | AI32: =SUM(O32:AH32)+M32 -> 213593 | AJ32: =SUM(N32:AH32) -> 227273 | AK32: =$F$27 -> 0.12 | AL32: =AI32+(AI32*AK32) -> 239224.16 | AM32: =AJ32+(AJ32*AK32) -> 254545.76
A33: 2 | B33: 13 | C33: 545 | D33: =B33*C33/1000 -> 7.085 | E33: =AL33/D33 -> 36532.511 | F33: 0.139 | G33: =(E33+(E33*F33))*D33 -> 294810.6 | H33: 580 | I33: =B33*H33/1000 -> 7.54 | J33: =AM33/I33 -> 36529.342 | K33: 0.139 | L33: =(J33+(J33*K33))*I33 -> 313716.18 | M33: =$E$2*(D33*1000) -> 113360 | N33: =$E$3*(I33*1000) -> 128180 | O33: =$E$4*I33*1000 -> 38454 | P33: =$E$5*I33 -> 30160 | Q33: =$E$7*B33 -> 494 | R33: =$E$8*B33 -> 130 | S33: =$E$9*(B33*4) -> 624 | T33: =$E$10*(I33*1000) -> 5278 | U33: =$E$11*(I33*1000) -> 3770 | V33: =$E$12 -> 2000 | W33: =$E$13 -> 1500 | X33: =$E$14*I33 -> 9048 | AB33: =$E$20*(B33/2) -> 422.5 | AC33: =I33*100 -> 754 | AD33: =$E$22*(B33*1.13) -> 6243.25 | AE33: =$E$23*(B33/2) -> 2275 | AF33: =$E$24*I33 -> 2639 | AG33: =$E$25*I33 -> 1131 | AH33: =$E$26*I33 -> 12818 | AI33: =SUM(O33:AH33)+M33 -> 231100.75 | AJ33: =SUM(N33:AH33) -> 245920.75 | AK33: =$F$27 -> 0.12 | AL33: =AI33+(AI33*AK33) -> 258832.84 | AM33: =AJ33+(AJ33*AK33) -> 275431.24
A34: 3 | B34: 14 | C34: 545 | D34: =B34*C34/1000 -> 7.63 | E34: =AL34/D34 -> 36492.991 | F34: 0.139 | G34: =(E34+(E34*F34))*D34 -> 317144.89 | H34: 580 | I34: =B34*H34/1000 -> 8.12 | J34: =AM34/I34 -> 36492.207 | K34: 0.139 | L34: =(J34+(J34*K34))*I34 -> 337504.74 | M34: =$E$2*(D34*1000) -> 122080 | N34: =$E$3*(I34*1000) -> 138040 | O34: =$E$4*I34*1000 -> 41412 | P34: =$E$5*I34 -> 32480 | Q34: =$E$7*B34 -> 532 | R34: =$E$8*B34 -> 140 | S34: =$E$9*(B34*4) -> 672 | T34: =$E$10*(I34*1000) -> 5684 | U34: =$E$11*(I34*1000) -> 4060 | V34: =$E$12 -> 2000 | W34: =$E$13 -> 1500 | X34: =$E$14*I34 -> 9744 | AB34: =$E$20*(B34/2) -> 455 | AC34: =I34*100 -> 812 | AD34: =$E$22*(B34*1.13) -> 6723.5 | AE34: =$E$23*(B34/2) -> 2450 | AF34: =$E$24*I34 -> 2842 | AG34: =$E$25*I34 -> 1218 | AH34: =$E$26*I34 -> 13804 | AI34: =SUM(O34:AH34)+M34 -> 248608.5 | AJ34: =SUM(N34:AH34) -> 264568.5 | AK34: =$F$27 -> 0.12 | AL34: =AI34+(AI34*AK34) -> 278441.52 | AM34: =AJ34+(AJ34*AK34) -> 296316.72
A35: 4 | B35: 15 | C35: 545 | D35: =B35*C35/1000 -> 8.175 | E35: =AL35/D35 -> 36458.74 | F35: 0.139 | G35: =(E35+(E35*F35))*D35 -> 339479.18 | H35: 580 | I35: =B35*H35/1000 -> 8.7 | J35: =AM35/I35 -> 36460.023 | K35: 0.139 | L35: =(J35+(J35*K35))*I35 -> 361293.31 | M35: =$E$2*(D35*1000) -> 130800 | N35: =$E$3*(I35*1000) -> 147900 | O35: =$E$4*I35*1000 -> 44370 | P35: =$E$5*I35 -> 34800 | Q35: =$E$7*B35 -> 570 | R35: =$E$8*B35 -> 150 | S35: =$E$9*(B35*4) -> 720 | T35: =$E$10*(I35*1000) -> 6090 | U35: =$E$11*(I35*1000) -> 4350 | V35: =$E$12 -> 2000 | W35: =$E$13 -> 1500 | X35: =$E$14*I35 -> 10440 | AB35: =$E$20*(B35/2) -> 487.5 | AC35: =I35*100 -> 870 | AD35: =$E$22*(B35*1.13) -> 7203.75 | AE35: =$E$23*(B35/2) -> 2625 | AF35: =$E$24*I35 -> 3045 | AG35: =$E$25*I35 -> 1305 | AH35: =$E$26*I35 -> 14790 | AI35: =SUM(O35:AH35)+M35 -> 266116.25 | AJ35: =SUM(N35:AH35) -> 283216.25 | AK35: =$F$27 -> 0.12 | AL35: =AI35+(AI35*AK35) -> 298050.2 | AM35: =AJ35+(AJ35*AK35) -> 317202.2
A36: 5 | B36: 16 | C36: 545 | D36: =B36*C36/1000 -> 8.72 | E36: =AL36/D36 -> 36428.771 | F36: 0.139 | G36: =(E36+(E36*F36))*D36 -> 361813.46 | H36: 580 | I36: =B36*H36/1000 -> 9.28 | J36: =AM36/I36 -> 36431.862 | K36: 0.139 | L36: =(J36+(J36*K36))*I36 -> 385081.87 | M36: =$E$2*(D36*1000) -> 139520 | N36: =$E$3*(I36*1000) -> 157760 | O36: =$E$4*I36*1000 -> 47328 | P36: =$E$5*I36 -> 37120 | Q36: =$E$7*B36 -> 608 | R36: =$E$8*B36 -> 160 | S36: =$E$9*(B36*4) -> 768 | T36: =$E$10*(I36*1000) -> 6496 | U36: =$E$11*(I36*1000) -> 4640 | V36: =$E$12 -> 2000 | W36: =$E$13 -> 1500 | X36: =$E$14*I36 -> 11136 | AB36: =$E$20*(B36/2) -> 520 | AC36: =I36*100 -> 928 | AD36: =$E$22*(B36*1.13) -> 7684 | AE36: =$E$23*(B36/2) -> 2800 | AF36: =$E$24*I36 -> 3248 | AG36: =$E$25*I36 -> 1392 | AH36: =$E$26*I36 -> 15776 | AI36: =SUM(O36:AH36)+M36 -> 283624 | AJ36: =SUM(N36:AH36) -> 301864 | AK36: =$F$27 -> 0.12 | AL36: =AI36+(AI36*AK36) -> 317658.88 | AM36: =AJ36+(AJ36*AK36) -> 338087.68
A37: 6 | B37: 17 | C37: 545 | D37: =B37*C37/1000 -> 9.265 | E37: =AL37/D37 -> 36402.327 | F37: 0.139 | G37: =(E37+(E37*F37))*D37 -> 384147.75 | H37: 580 | I37: =B37*H37/1000 -> 9.86 | J37: =AM37/I37 -> 36407.014 | K37: 0.139 | L37: =(J37+(J37*K37))*I37 -> 408870.43 | M37: =$E$2*(D37*1000) -> 148240 | N37: =$E$3*(I37*1000) -> 167620 | O37: =$E$4*I37*1000 -> 50286 | P37: =$E$5*I37 -> 39440 | Q37: =$E$7*B37 -> 646 | R37: =$E$8*B37 -> 170 | S37: =$E$9*(B37*4) -> 816 | T37: =$E$10*(I37*1000) -> 6902 | U37: =$E$11*(I37*1000) -> 4930 | V37: =$E$12 -> 2000 | W37: =$E$13 -> 1500 | X37: =$E$14*I37 -> 11832 | AB37: =$E$20*(B37/2) -> 552.5 | AC37: =I37*100 -> 986 | AD37: =$E$22*(B37*1.13) -> 8164.25 | AE37: =$E$23*(B37/2) -> 2975 | AF37: =$E$24*I37 -> 3451 | AG37: =$E$25*I37 -> 1479 | AH37: =$E$26*I37 -> 16762 | AI37: =SUM(O37:AH37)+M37 -> 301131.75 | AJ37: =SUM(N37:AH37) -> 320511.75 | AK37: =$F$27 -> 0.12 | AL37: =AI37+(AI37*AK37) -> 337267.56 | AM37: =AJ37+(AJ37*AK37) -> 358973.16
A38: 7 | B38: 18 | C38: 545 | D38: =B38*C38/1000 -> 9.81 | E38: =AL38/D38 -> 36378.822 | F38: 0.139 | G38: =(E38+(E38*F38))*D38 -> 406482.04 | H38: 580 | I38: =B38*H38/1000 -> 10.44 | J38: =AM38/I38 -> 36384.927 | K38: 0.139 | L38: =(J38+(J38*K38))*I38 -> 432658.99 | M38: =$E$2*(D38*1000) -> 156960 | N38: =$E$3*(I38*1000) -> 177480 | O38: =$E$4*I38*1000 -> 53244 | P38: =$E$5*I38 -> 41760 | Q38: =$E$7*B38 -> 684 | R38: =$E$8*B38 -> 180 | S38: =$E$9*(B38*4) -> 864 | T38: =$E$10*(I38*1000) -> 7308 | U38: =$E$11*(I38*1000) -> 5220 | V38: =$E$12 -> 2000 | W38: =$E$13 -> 1500 | X38: =$E$14*I38 -> 12528 | AB38: =$E$20*(B38/2) -> 585 | AC38: =I38*100 -> 1044 | AD38: =$E$22*(B38*1.13) -> 8644.5 | AE38: =$E$23*(B38/2) -> 3150 | AF38: =$E$24*I38 -> 3654 | AG38: =$E$25*I38 -> 1566 | AH38: =$E$26*I38 -> 17748 | AI38: =SUM(O38:AH38)+M38 -> 318639.5 | AJ38: =SUM(N38:AH38) -> 339159.5 | AK38: =$F$27 -> 0.12 | AL38: =AI38+(AI38*AK38) -> 356876.24 | AM38: =AJ38+(AJ38*AK38) -> 379858.64
A39: 8 | B39: 20 | C39: 545 | D39: =B39*C39/1000 -> 10.9 | E39: =AL39/D39 -> 36338.862 | F39: 0.139 | G39: =(E39+(E39*F39))*D39 -> 451150.61 | H39: 580 | I39: =B39*H39/1000 -> 11.6 | J39: =AM39/I39 -> 36347.379 | K39: 0.139 | L39: =(J39+(J39*K39))*I39 -> 480236.11 | M39: =$E$2*(D39*1000) -> 174400 | N39: =$E$3*(I39*1000) -> 197200 | O39: =$E$4*I39*1000 -> 59160 | P39: =$E$5*I39 -> 46400 | Q39: =$E$7*B39 -> 760 | R39: =$E$8*B39 -> 200 | S39: =$E$9*(B39*4) -> 960 | T39: =$E$10*(I39*1000) -> 8120 | U39: =$E$11*(I39*1000) -> 5800 | V39: =$E$12 -> 2000 | W39: =$E$13 -> 1500 | X39: =$E$14*I39 -> 13920 | AB39: =$E$20*(B39/2) -> 650 | AC39: =I39*100 -> 1160 | AD39: =$E$22*(B39*1.13) -> 9605 | AE39: =$E$23*(B39/2) -> 3500 | AF39: =$E$24*I39 -> 4060 | AG39: =$E$25*I39 -> 1740 | AH39: =$E$26*I39 -> 19720 | AI39: =SUM(O39:AH39)+M39 -> 353655 | AJ39: =SUM(N39:AH39) -> 376455 | AK39: =$F$27 -> 0.12 | AL39: =AI39+(AI39*AK39) -> 396093.6 | AM39: =AJ39+(AJ39*AK39) -> 421629.6
A40: 9 | B40: 22 | C40: 545 | D40: =B40*C40/1000 -> 11.99 | E40: =AL40/D40 -> 36306.168 | F40: 0.139 | G40: =(E40+(E40*F40))*D40 -> 495819.18 | H40: 580 | I40: =B40*H40/1000 -> 12.76 | J40: =AM40/I40 -> 36316.658 | K40: 0.139 | L40: =(J40+(J40*K40))*I40 -> 527813.24 | M40: =$E$2*(D40*1000) -> 191840 | N40: =$E$3*(I40*1000) -> 216920 | O40: =$E$4*I40*1000 -> 65076 | P40: =$E$5*I40 -> 51040 | Q40: =$E$7*B40 -> 836 | R40: =$E$8*B40 -> 220 | S40: =$E$9*(B40*4) -> 1056 | T40: =$E$10*(I40*1000) -> 8932 | U40: =$E$11*(I40*1000) -> 6380 | V40: =$E$12 -> 2000 | W40: =$E$13 -> 1500 | X40: =$E$14*I40 -> 15312 | AB40: =$E$20*(B40/2) -> 715 | AC40: =I40*100 -> 1276 | AD40: =$E$22*(B40*1.13) -> 10565.5 | AE40: =$E$23*(B40/2) -> 3850 | AF40: =$E$24*I40 -> 4466 | AG40: =$E$25*I40 -> 1914 | AH40: =$E$26*I40 -> 21692 | AI40: =SUM(O40:AH40)+M40 -> 388670.5 | AJ40: =SUM(N40:AH40) -> 413750.5 | AK40: =$F$27 -> 0.12 | AL40: =AI40+(AI40*AK40) -> 435310.96 | AM40: =AJ40+(AJ40*AK40) -> 463400.56
A41: 10 | B41: 24 | C41: 545 | D41: =B41*C41/1000 -> 13.08 | E41: =AL41/D41 -> 36278.924 | F41: 0.139 | G41: =(E41+(E41*F41))*D41 -> 540487.76 | H41: 580 | I41: =B41*H41/1000 -> 13.92 | J41: =AM41/I41 -> 36291.057 | K41: 0.139 | L41: =(J41+(J41*K41))*I41 -> 575390.36 | M41: =$E$2*(D41*1000) -> 209280 | N41: =$E$3*(I41*1000) -> 236640 | O41: =$E$4*I41*1000 -> 70992 | P41: =$E$5*I41 -> 55680 | Q41: =$E$7*B41 -> 912 | R41: =$E$8*B41 -> 240 | S41: =$E$9*(B41*4) -> 1152 | T41: =$E$10*(I41*1000) -> 9744 | U41: =$E$11*(I41*1000) -> 6960 | V41: =$E$12 -> 2000 | W41: =$E$13 -> 1500 | X41: =$E$14*I41 -> 16704 | AB41: =$E$20*(B41/2) -> 780 | AC41: =I41*100 -> 1392 | AD41: =$E$22*(B41*1.13) -> 11526 | AE41: =$E$23*(B41/2) -> 4200 | AF41: =$E$24*I41 -> 4872 | AG41: =$E$25*I41 -> 2088 | AH41: =$E$26*I41 -> 23664 | AI41: =SUM(O41:AH41)+M41 -> 423686 | AJ41: =SUM(N41:AH41) -> 451046 | AK41: =$F$27 -> 0.12 | AL41: =AI41+(AI41*AK41) -> 474528.32 | AM41: =AJ41+(AJ41*AK41) -> 505171.52
A42: 11 | B42: 26 | C42: 545 | D42: =B42*C42/1000 -> 14.17 | E42: =AL42/D42 -> 36255.87 | F42: 0.139 | G42: =(E42+(E42*F42))*D42 -> 585156.33 | H42: 580 | I42: =B42*H42/1000 -> 15.08 | J42: =AM42/I42 -> 36269.395 | K42: 0.139 | L42: =(J42+(J42*K42))*I42 -> 622967.48 | M42: =$E$2*(D42*1000) -> 226720 | N42: =$E$3*(I42*1000) -> 256360 | O42: =$E$4*I42*1000 -> 76908 | P42: =$E$5*I42 -> 60320 | Q42: =$E$7*B42 -> 988 | R42: =$E$8*B42 -> 260 | S42: =$E$9*(B42*4) -> 1248 | T42: =$E$10*(I42*1000) -> 10556 | U42: =$E$11*(I42*1000) -> 7540 | V42: =$E$12 -> 2000 | W42: =$E$13 -> 1500 | X42: =$E$14*I42 -> 18096 | AB42: =$E$20*(B42/2) -> 845 | AC42: =I42*100 -> 1508 | AD42: =$E$22*(B42*1.13) -> 12486.5 | AE42: =$E$23*(B42/2) -> 4550 | AF42: =$E$24*I42 -> 5278 | AG42: =$E$25*I42 -> 2262 | AH42: =$E$26*I42 -> 25636 | AI42: =SUM(O42:AH42)+M42 -> 458701.5 | AJ42: =SUM(N42:AH42) -> 488341.5 | AK42: =$F$27 -> 0.12 | AL42: =AI42+(AI42*AK42) -> 513745.68 | AM42: =AJ42+(AJ42*AK42) -> 546942.48
A43: 12 | B43: 28 | C43: 545 | D43: =B43*C43/1000 -> 15.26 | E43: =AL43/D43 -> 36236.11 | F43: 0.139 | G43: =(E43+(E43*F43))*D43 -> 629824.9 | H43: 580 | I43: =B43*H43/1000 -> 16.24 | J43: =AM43/I43 -> 36250.828 | K43: 0.139 | L43: =(J43+(J43*K43))*I43 -> 670544.61 | M43: =$E$2*(D43*1000) -> 244160 | N43: =$E$3*(I43*1000) -> 276080 | O43: =$E$4*I43*1000 -> 82824 | P43: =$E$5*I43 -> 64960 | Q43: =$E$7*B43 -> 1064 | R43: =$E$8*B43 -> 280 | S43: =$E$9*(B43*4) -> 1344 | T43: =$E$10*(I43*1000) -> 11368 | U43: =$E$11*(I43*1000) -> 8120 | V43: =$E$12 -> 2000 | W43: =$E$13 -> 1500 | X43: =$E$14*I43 -> 19488 | AB43: =$E$20*(B43/2) -> 910 | AC43: =I43*100 -> 1624 | AD43: =$E$22*(B43*1.13) -> 13447 | AE43: =$E$23*(B43/2) -> 4900 | AF43: =$E$24*I43 -> 5684 | AG43: =$E$25*I43 -> 2436 | AH43: =$E$26*I43 -> 27608 | AI43: =SUM(O43:AH43)+M43 -> 493717 | AJ43: =SUM(N43:AH43) -> 525637 | AK43: =$F$27 -> 0.12 | AL43: =AI43+(AI43*AK43) -> 552963.04 | AM43: =AJ43+(AJ43*AK43) -> 588713.44
... A121: 90 | B121: 184 | C121: 545 | D121: =B121*C121/1000 -> 100.28 | E121: =AL121/D121 -> 36018.32 | F121: 0.139 | G121: =(E121+(E121*F121))*D121 -> 4113973.6 | H121: 580 | I121: =B121*H121/1000 -> 106.72 | J121: =AM121/I121 -> 36046.18 | K121: 0.139 | L121: =(J121+(J121*K121))*I121 -> 4381560.2 | M121: =$E$2*(D121*1000) -> 1604480 | N121: =$E$3*(I121*1000) -> 1814240 | O121: =$E$4*I121*1000 -> 544272 | P121: =$E$5*I121 -> 426880 | Q121: =$E$7*B121 -> 6992 | R121: =$E$8*B121 -> 1840 | S121: =$E$9*(B121*4) -> 8832 | T121: =$E$10*(I121*1000) -> 74704 | U121: =$E$11*(I121*1000) -> 53360 | V121: =$E$12 -> 2000 | W121: =$E$13 -> 1500 | X121: =$E$14*I121 -> 128064 | AB121: =$E$20*(B121/2) -> 5980 | AC121: =I121*100 -> 10672 | AD121: =$E$22*(B121*1.13) -> 88366 | AE121: =$E$23*(B121/2) -> 32200 | AF121: =$E$24*I121 -> 37352 | AG121: =$E$25*I121 -> 16008 | AH121: =$E$26*I121 -> 181424 | AI121: =SUM(O121:AH121)+M121 -> 3224926 | AJ121: =SUM(N121:AH121) -> 3434686 | AK121: =$F$27 -> 0.12 | AL121: =AI121+(AI121*AK121) -> 3611917.1 | AM121: =AJ121+(AJ121*AK121) -> 3846848.3

Sheet Sheet1
A1: Here's a detailed and professional "Industrial HT Consumer Solar Quotation Format" tailored specifically for High Tension (HT) consumers, such as large industries, factories, or commercial units in India. This format is designed for EPC contractors offering grid-connected solar power systems, especially for capacities above 100 kW.
A5: 🔷 INDUSTRIAL HT CONSUMER SOLAR QUOTATION FORMAT
N6: Module | O6: VIKRAM | R6: 14.9 | S6: 540 | T6: 101
A7: 📌 1. Cover Page | N7: inverter | O7: Sungrow | S7: 540 | T7: 112 | U7: =T7*S7 -> 60480
A9: Company Name & Logo | O9: =368*545 -> 200560
W10: KW | X10: Rate | Y10: Avg
A11: Client Name / Company Name | M11: Sr No | N11: ITEM NAME | O11: Count | P11: Amount | Q11: UNIT | R11: Total | S11: GST% | T11: GST | U11: NET AMOUNT | W11: 125 kw | X11: 285000 | Y11: =X11/125000 -> 2.28
M12: 1 | N12: SOLAR MODULE | O12: =514*595 -> 305830 | P12: 15.1 | Q12: RS/WATT | R12: =O12*P12 -> 4618033 | S12: 0.12 | T12: =R12*S12 -> 554163.96 | U12: =R12+T12 -> 5172197 | W12: 100 kw | X12: 267000 | Y12: =X12/100000 -> 2.67
A13: Quotation Title: "Proposal for Grid-Connected Solar PV System – HT Consumer" | K13: 20300 | M13: 2 | N13: INVERTER | O13: =O12 -> 305830 | P13: 2.67 | Q13: RS/WATT | R13: =O13*P13 -> 816566.1 | S13: 0.12 | T13: =R13*S13 -> 97987.932 | U13: =R13+T13 -> 914554.03 | W13: 75 kw | X13: 223000 | Y13: =X13/75000 -> 2.9733333
K14: =18*550 -> 9900 | M14: 3 | N14: MODULE MOUNTING STRUCTURE | O14: 7500 | P14: 75 | Q14: Rs/Kw | R14: =O14*P14 -> 562500 | S14: 0.18 | T14: =R14*S14 -> 101250 | U14: =R14+T14 -> 663750
A15: Quotation Reference No. | P15: 76 | Q15: RS/KG | R15: =O15*P15 -> 0 | S15: 0.18 | T15: =R15*S15 -> 0 | U15: =R15+T15 -> 0
M17: 5 | N17: BASE PLATE | O17: 250 | P17: 60 | Q17: RS/NOS | R17: =O17*P17 -> 15000 | S17: 0.18 | T17: =R17*S17 -> 2700 | U17: =R17+T17 -> 17700
A18: Date of Issue | M18: 6 | N18: J BOULT | O18: =O17*4 -> 1000 | P18: 10 | Q18: RS/NOS | R18: =O18*P18 -> 10000 | S18: 0.18 | T18: =R18*S18 -> 1800 | U18: =R18+T18 -> 11800
M19: 7 | N19: ANCORE FASTNER | O19: =514*4.1 -> 2107.4 | P19: 15 | Q19: RS/NOS | R19: =O19*P19 -> 31611 | S19: 0.18 | T19: =R19*S19 -> 5689.98 | U19: =R19+T19 -> 37300.98
A20: Prepared by | M20: 8 | N20: ACDB | O20: =O12 -> 305830 | P20: 0.8 | Q20: RS/WATT | R20: =O20*P20 -> 244664 | S20: 0.18 | T20: =R20*S20 -> 44039.52 | U20: =R20+T20 -> 288703.52
M21: 9 | N21: DCDB | O21: =O12 -> 305830 | P21: 0.3 | Q21: RS/WATT | R21: =O21*P21 -> 91749 | S21: 0.18 | T21: =R21*S21 -> 16514.82 | U21: =R21+T21 -> 108263.82
A22: Prepared for | M22: 10 | N22: LIGHTNING ARRESTOR | O22: 1 | P22: 26500 | Q22: RS/NOS | R22: =O22*P22 -> 26500 | S22: 0.18 | T22: =R22*S22 -> 4770 | U22: =R22+T22 -> 31270
N23: EARTHING ROAD
M24: 11 | N24: DC CABLE | O24: 50 | P24: 427 | Q24: RS/MTR | R24: =O24*P24 -> 21350 | S24: 0.18 | T24: =R24*S24 -> 3843 | U24: =R24+T24 -> 25193
A25: Valid Till Date | M25: 12 | N25: AC CABLE | O25: 20 | P25: 1010 | Q25: RS/MTR | R25: =O25*P25 -> 20200 | S25: 0.18 | T25: =R25*S25 -> 3636 | U25: =R25+T25 -> 23836
M26: 13 | N26: AC CABLE- 2 | O26: 750 | P26: 42 | Q26: RS/MTR | R26: =O26*P26 -> 31500 | S26: 0.18 | T26: =R26*S26 -> 5670 | U26: =R26+T26 -> 37170
M27: 14 | N27: EARTHING CABLE / STRIP | O27: 100 | P27: 80 | Q27: RS/MTR | R27: =O27*P27 -> 8000 | S27: 0.18 | T27: =R27*S27 -> 1440 | U27: =R27+T27 -> 9440
M28: 15 | N28: LA CABLE / STRIP | O28: 50 | P28: 40 | Q28: RS/MTR | R28: =O28*P28 -> 2000 | S28: 0.18 | T28: =R28*S28 -> 360 | U28: =R28+T28 -> 2360
A29: 📌 2. Index | M29: 16 | N29: CABLE TRAY | O29: 200 | P29: 60 | Q29: RS/NOS | R29: =O29*P29 -> 12000 | S29: 0.18 | T29: =R29*S29 -> 2160 | U29: =R29+T29 -> 14160
M30: 17 | N30: CONDUITE | O30: 200 | P30: 280 | Q30: RS/MTR | R30: =O30*P30 -> 56000 | S30: 0.18 | T30: =R30*S30 -> 10080 | U30: =R30+T30 -> 66080
N31: WALK WAY
A32: 1. Executive Summary | M32: 18 | N32: MC4 CONNECTOR | O32: 120 | P32: 24 | Q32: RS/NOS | R32: =O32*P32 -> 2880 | S32: 0.18 | T32: =R32*S32 -> 518.4 | U32: =R32+T32 -> 3398.4
M33: 19 | N33: ISOLATION | O33: 8 | P33: 3700 | Q33: RS/NOS | R33: =O33*P33 -> 29600 | S33: 0.18 | T33: =R33*S33 -> 5328 | U33: =R33+T33 -> 34928
A34: 2. Site Details | M34: 20 | N34: FOUNDATION BLOCK | O34: 1 | P34: 1000 | Q34: RS/NOS | R34: =O34*P34 -> 1000 | S34: 0.18 | T34: =R34*S34 -> 180 | U34: =R34+T34 -> 1180
M35: 21 | N35: OTHER MISS. ITEM | O35: 30 | P35: 100 | Q35: - | R35: =O35*P35 -> 3000 | S35: 0.18 | T35: =R35*S35 -> 540 | U35: =R35+T35 -> 3540
A36: 3. Technical Proposal | M36: 22 | N36: Transport | O36: 2 | P36: 2000 | R36: =O36*P36 -> 4000 | S36: 0.18 | T36: =R36*S36 -> 720 | U36: =R36+T36 -> 4720
M37: 23 | N37: Installation Charges | O37: =O12/1000 -> 305.83 | P37: 1700 | R37: =O37*P37 -> 519911 | S37: 0.18 | T37: =R37*S37 -> 93583.98 | U37: =R37+T37 -> 613494.98
A38: 4. Financial Proposal | M38: 24 | N38: IFP CHARGES | O38: 10 | P38: 350 | Q38: RS/NOS | R38: =O38*P38 -> 3500 | S38: 0.18 | T38: =R38*S38 -> 630 | U38: =R38+T38 -> 4130
M39: 25 | N39: EARTHING BOARING CHARGES | O39: 350 | P39: 400 | Q39: rs/mtr | R39: =O39*P39 -> 140000 | S39: 0.18 | T39: =R39*S39 -> 25200 | U39: =R39+T39 -> 165200
A40: 5. Net Metering & DISCOM Charges | M40: 26 | O40: =O33 -> 8 | P40: 4500 | Q40: rs/nOs | R40: =O40*P40 -> 36000 | S40: 0 | T40: =R40*S40 -> 0 | U40: =R40+T40 -> 36000
M41: 27 | O41: =O13/1000 -> 305.83 | P41: 400 | Q41: RS/KW | R41: =O41*P41 -> 122332 | S41: 0 | T41: =R41*S41 -> 0 | U41: =R41+T41 -> 122332
A42: 6. Commercial Terms & Conditions | M42: 28 | O42: 0 | P42: =17500+12000 -> 29500 | R42: =O42*P42 -> 0 | T42: =R42*S42 -> 0 | U42: =R42+T42 -> 0
M43: 29 | O43: 0 | P43: 15300 | R43: =O43*P43 -> 0 | T43: =R43*S43 -> 0 | U43: =R43+T43 -> 0
A44: 7. Warranty & AMC Details | M44: 30 | N44: Commissioning Charges | O44: =SUM(U12:U43) -> 8412701.7 | P44: 0.15 | Q44: =O44*P44 -> 1261905.3 | R44: =O44+Q44 -> 9674606.9 | S44: 0.05 | T44: =Q44*S44 -> 63095.263 | U44: =R44+T44 -> 9737702.2
R45: =R44/O37 -> 31633.937 | U45: =U44/O37 -> 31840.245
A46: 8. Project Timeline
A48: 9. Required Approvals & Documentation
A50: 10. Bank Details
A52: 11. Annexures (Layouts, Datasheets, Certificates)
A56: 📌 3. Executive Summary
A58: System Size (kW or MW)
A60: Estimated Energy Generation (per year)
A62: Expected Savings
A64: Payback Period
A66: CO₂ Emissions Saved
A68: Summary of Cost
A72: 📌 4. Site Details
... A108: 📌 6. Financial Proposal
A110: Description | B110: Details
A111: System Capacity (kW)
A112: Price per kW (₹)
A113: Total System Cost (₹)
A114: GST % & Amount (₹)
A115: Gross Total (₹)
A116: Subsidy (if applicable)
A117: Net Payable Amount (₹)
A120: 📌 7. Net Metering & DISCOM Charges
A122: Approximate Application & Processing Charges
A124: Feasibility Report Charges
A126: HT Meter CT/PT Replacement (if applicable)
A128: Net Metering Cost Estimates
... A134: 📌 8. Commercial Terms & Conditions
A136: Term | B136: Details
A137: Delivery Time | B137: e.g., 10–12 weeks from PO
A138: Payment Terms | B138: e.g., 30% Advance, 60% on Delivery, 10% on Commissioning
A139: Validity of Quotation | B139: e.g., 30 Days
A140: Installation & Commissioning | B140: Included / Excluded
A141: Insurance During Project | B141: Included / By Client
A142: Performance Guarantee | B142: e.g., 80% PR for 25 years
A143: AMC After Warranty | B143: Optional – ₹/Year
A146: 📌 9. Warranty & AMC
A148: Module Warranty: 25 Years (Performance)
A150: Inverter Warranty: 5–10 Years
A152: Workmanship Warranty: 1 Year
A154: Optional AMC Plans with Pricing
A158: 📌 10. Project Timeline
A160: Milestone | B160: Duration
A161: Engineering & Design | B161: 1 Week
A162: Procurement | B162: 3–4 Weeks
A163: Installation & Testing | B163: 2–3 Weeks
A164: Net Metering & Synchronization | B164: 2–4 Weeks
A167: 📌 11. Required Approvals & Documentation
A169: CEIG Approval (if >10kW or HT)
A171: Net Metering Approval
A173: Single Line Diagram (SLD)
A175: Load Flow Study Report
A177: Safety Certificate
A179: Work Completion Certificate
A183: 📌 12. Bank Details
A185: (For Advance Payment)
A187: Bank Name
A189: Account Name
A191: Account Number
... A213: Would you like a downloadable Word or Excel template for this format? Or a customized quotation PDF with your company details and logo?

Sheet Sheet2
R15: 181260
M16: 202760 | N16: TOTAL | R16: 19000
L17: 26000 | M17: 155000 | R17: 7000
M18: =M16-M17 -> 47760 | N18: =M18-L17 -> 21760 | R18: =SUM(R15:R17) -> 207260
R19: 155000
R20: 26000
R21: =R18-R19-R20 -> 26260
